Workbook

Sheet Catalogo
A1: ID | B1: Tipo | C1: SKU | D1: Nombre | E1: Publicado | F1: ¿Está destacado? | G1: Visibilidad en el catálogo | H1: Descripción corta | I1: Descripción | J1: Día en que empieza el precio rebajado | K1: Día en que termina el precio rebajado | L1: Estado del impuesto | M1: Clase de impuesto | N1: ¿En inventario? | O1: Inventario | P1: Cantidad de bajo inventario | Q1: ¿Permitir reservas de productos agotados? | R1: ¿Vendido individualmente? | S1: Peso (kg) | T1: Longitud (cm) | U1: Anchura (cm) | V1: Altura (cm) | W1: ¿Permitir valoraciones de clientes? | X1: Nota de compra | Y1: Precio rebajado | Z1: Precio normal | AA1: Categorías | AB1: Etiquetas | AC1: Clase de envío | AD1: Imágenes | AE1: Límite de descargas | AF1: Días de caducidad de la descarga | AG1: Superior | AH1: Productos agrupados | AI1: Ventas dirigidas | AJ1: Ventas cruzadas | AK1: URL externa | AL1: Texto del botón | AM1: Posición | AN1: Nombre del atributo 1 | AO1: Valor(es) del atributo 1 | AP1: Atributo visible 1 | AQ1: Atributo global 1 | AR1: Nombre de la descarga 1 | AS1: URL de la descarga 1
B2: simple | D2: Hoddie F&T | E2: 1 | F2: 0 | G2: visible | H2: Excelente hoddie para el frio | L2: taxable | M2: parent | N2: 1 | Q2: 0 | R2: 0 | W2: 1 | Z2: 750 | AA2: Hoddies | AD2: https://dominio.com/wp-content/uploads/2021/07/hoddie-1.jpg, https://dominio.com/wp-content/uploads/2021/07/hoddie-2.jpg, https://dominio.com/wp-content/uploads/2021/07/hoddie-3.jpg | AM2: 0

Sheet CATALOGO PAGINA
A1: ID | B1: Type | C1: SKU | D1: Name | E1: Published | F1: Is featured? | G1: Visibility in catalog | H1: Short description | I1: Description | J1: Date sale price starts | K1: Date sale price ends | L1: Tax status | M1: Tax class | N1: In stock? | O1: Stock | P1: Low stock amount | Q1: Backorders allowed? | R1: Sold individually? | S1: Weight (kg) | T1: Length (cm) | U1: Width (cm) | V1: Height (cm) | W1: Allow customer reviews? | X1: Purchase note | Y1: Sale price | Z1: Regular price | AA1: Categories | AB1: Images | AC1: Meta: _product_location | AD1: Meta: _items_per_products | AE1: Meta: product_step | AF1: Meta: _wpd_ai_product_cost | AG1: % de descuento
B2: simple | C2: FD853 | D2: Tall wall sanitizing shoe & Boot Mat - FD853 | E2: 0 | F2: 0 | G2: hidden | H2: Tall wall sanitizing shoe & Boot Mat | I2: Sanitizing mat | N2: 0 | O2: 0 | Z2: 2.99 | AA2: Mats | AB2: https://fantasydiscountwholesale.com/wp-content/uploads/2023/10/FD853.jpeg | AC2: 1 | AD2: 6 | AE2: =AD2 -> 6 | AF2: 3.41 | AG2: =AF2*-0.707+AF2 -> 0.99913 | AH2: =Z2*0.1-Z2 -> -2.691 | AI2: =AF2*0.05+AF2 -> 3.5805 | AJ2: =1-AF2/Z2 -> -0.14046823
B3: simple | C3: FD1013S | D3: TOTUMAS PEQUENA / GUIRA SMALL - FD1013S | E3: 1 | F3: 0 | G3: visible | H3: These small totumas are natural dried fruits carved by hand | I3: A compact and traditional percussion instrument handcrafted from a small gourd. With its unique shape and sound, this guira adds a distinctive rhythmic element to your music. | N3: 1 | O3: 1000 | Z3: 0.85 | AA3: Miscellaneous | AB3: https://fantasydiscountwholesale.com/wp-content/uploads/2023/10/FD1013S.jpeg | AC3: 1 | AD3: 12 | AE3: =AD3 -> 12 | AF3: 0.29 | AG3: =AF3*1.6+AF3 -> 0.754 | AH3: =Z3*0.1-Z3 -> -0.765 | AI3: =AF3*0.4+AF3 -> 0.406 | AJ3: =1-AF3/Z3 -> 0.65882353
B4: simple | C4: FD1013M | D4: TOTUMAS MEDIANA / GUIRA MEDIUM - FD1013M | E4: 1 | F4: 0 | G4: visible | H4: TOTUMAS MEDIANA / GUIRA MEDIUM - FD1013M | I4: Totumas Mediana / Guira Medium – FD1013M is a versatile, durable bowl ideal for serving soups, stews, or traditional dishes. Perfect for restaurants, markets, and wholesale distribution. Lightweight and reusable. | N4: 1 | O4: 1000 | Z4: 1.5 | AA4: Miscellaneous | AB4: https://fantasydiscountwholesale.com/wp-content/uploads/2023/10/FD1013M.jpeg | AC4: 1 | AD4: 12 | AE4: =AD4 -> 12 | AF4: 0.29 | AG4: =AF4*3.3+AF4 -> 1.247 | AH4: =Z4*0.1-Z4 -> -1.35 | AI4: =AF4*0.4+AF4 -> 0.406 | AJ4: =1-AF4/Z4 -> 0.80666667
B5: simple | C5: FD1013L | D5: TOTUMAS GRANDE / GUIRA LARGE - FD1013L | E5: 1 | F5: 0 | G5: visible | H5: TOTUMAS GRANDE / GUIRA LARGE - FD1013L | I5: These large guira instruments are crafted from sizable gourds, offering a rich and distinctive percussion sound. Handmade with care, they are perfect for musicians looking to add an authentic and captivating element to their music. | N5: 1 | O5: 1000 | Z5: 2 | AA5: Miscellaneous | AB5: https://fantasydiscountwholesale.com/wp-content/uploads/2023/10/FD1013L.jpeg | AC5: 1 | AD5: 12 | AE5: =AD5 -> 12 | AF5: 0.29 | AG5: =AF5*5.02+AF5 -> 1.7458 | AH5: =Z5*0.1-Z5 -> -1.8 | AI5: =AF5*0.4+AF5 -> 0.406 | AJ5: =1-AF5/Z5 -> 0.855
B6: simple | C6: CN91092-A | D6: Orange Oven Cleaner Heavy Duty 12OZ - CN91092-A | E6: 0 | F6: 0 | G6: hidden | H6: Orange Oven Cleaner Heavy Duty 12OZ - CN91092-A | I6: Orange Oven Cleaner Heavy Duty 12oz (CN91092-A) delivers powerful grease-cutting action for tough, baked-on messes. Its citrus formula cleans ovens, grills, and stovetops effectively. Ideal for retail, household use, and wholesale or discount stores. | N6: 0 | O6: 0 | Z6: 1.49 | AA6: cleaning supplies | AB6: https://fantasydiscountwholesale.com/wp-content/uploads/2025/06/CN91092-A.jpg | AC6: 1 | AD6: 12 | AE6: =AD6 -> 12 | AF6: 0.99 | AG6: =AF6*0.4+AF6 -> 1.386 | AH6: =Z6*0.1-Z6 -> -1.341 | AI6: =AF6*0.4+AF6 -> 1.386 | AJ6: =1-AF6/Z6 -> 0.33557047
B7: simple | C7: 41661 | D7: Roma Liquid Detergent 33.8OZ - 41661 | E7: 0 | F7: 0 | G7: hidden | H7: Roma Liquid Detergent 33.8OZ - 41661 | I7: Roma Liquid Detergent 33.8oz (41661) offers powerful cleaning for all types of laundry, removing tough stains while being gentle on fabrics. Leaves clothes fresh and bright. Ideal for retail, household use, and wholesale or discount stores. | N7: 0 | O7: 0 | Z7: 3.07 | AA7: cleaning supplies | AB7: https://fantasydiscountwholesale.com/wp-content/uploads/2025/06/41661.jpg | AC7: 1 | AD7: 6 | AE7: =AD7 -> 6 | AF7: 2.05 | AG7: =AF7*0.4+AF7 -> 2.87 | AH7: =Z7*0.1-Z7 -> -2.763 | AI7: =AF7*0.4+AF7 -> 2.87 | AJ7: =1-AF7/Z7 -> 0.33224756
B8: simple | C8: FD1606 | D8: Entrance door mat - FD1606 | E8: 1 | F8: 0 | G8: visible | H8: Entrance door mat- Chef 45*70 cm | I8: Charming entrance door mat featuring a chef design, measuring 45x70 cm. Perfect for kitchens or entryways, this mat traps dirt and moisture. Made with durable materials and a non-slip backing for added safety. Easy to clean and maintain, enhancing any home's decor. | N8: 1 | O8: 1000 | Z8: 3.5 | AA8: Mats | AB8: https://fantasydiscountwholesale.com/wp-content/uploads/2023/10/FD1606.jpeg | AC8: 1-1 | AD8: 12 | AE8: =AD8 -> 12 | AF8: 1.4 | AG8: =AF8*1+AF8 -> 2.8 | AH8: =Z8*0.1-Z8 -> -3.15 | AI8: =AF8*0.4+AF8 -> 1.96 | AJ8: =1-AF8/Z8 -> 0.6
B9: simple | C9: 801440 | D9: COB LED Light Switch (Magnetic Back) Cordless - 801440 | E9: 1 | F9: 0 | G9: visible | H9: COB LED Light Switch (Magnetic Back) Cordless | I9: Installs virtually anywhere, portable magnet mounts on the back, No electrician Needed | N9: 1 | O9: 1000 | Z9: 1.5 | AA9: Miscellaneous | AB9: https://fantasydiscountwholesale.com/wp-content/uploads/2023/10/801440-1.jpeg | AC9: 1-1 | AD9: 12 | AE9: =AD9 -> 12 | AF9: 0.98 | AG9: =AF9*0.4+AF9 -> 1.372 | AH9: =Z9*0.1-Z9 -> -1.35 | AI9: =AF9*0.4+AF9 -> 1.372 | AJ9: =1-AF9/Z9 -> 0.34666667
B10: simple | C10: 8888 | D10: scruber salvauñas - 8888 SA-64 | E10: 1 | F10: 0 | G10: visible | H10: Esponja Salvauña - SA-64 | I10: Esponja Salvaluna – SA‑64: Dual-use cleaning sponge designed to protect nails while scrubbing. Combines a soft cellulose side with a gentle abrasive surface. Ideal for wholesale to cleaning and kitchen goods retailers. | N10: 1 | O10: 1000 | Z10: 0.5 | AA10: cleaning supplies | AB10: https://fantasydiscountwholesale.com/wp-content/uploads/2025/06/8888.jpg | AC10: 1-1 | AD10: 48 | AE10: =AD10 -> 48 | AF10: 0.36 | AG10: =AF10*0.3+AF10 -> 0.468 | AH10: =Z10*0.1-Z10 -> -0.45 | AI10: =AF10*0.4+AF10 -> 0.504 | AJ10: =1-AF10/Z10 -> 0.28
B11: simple | C11: 6134 | D11: SAPOLIO LIME CLEANER (SACASARRO) 12/500ML sa-43 - 6134 | E11: 1 | F11: 0 | G11: visible | H11: SAPOLIO LIME CLEANER (SACASARRO) 12/500ML - 6134 | I11: Softsoap Aquarium Series combines enchanting designs from the sea with Antibacterial liquid soap. It contains germ fighting ingredient to provide strong antibacterial protection. Like other Softsoap products, Softsoap Aquarium Series liquid soap contains light moisturizers to help leave your hands clean and soft. | N11: 1 | O11: 1000 | Z11: 1.75 | AA11: cleaning supplies | AB11: https://fantasydiscountwholesale.com/wp-content/uploads/2023/10/6134.jpeg | AC11: 1-2 | AD11: 12 | AE11: =AD11 -> 12 | AF11: 1.34 | AG11: =AF11*0.25+AF11 -> 1.675 | AH11: =Z11*0.1-Z11 -> -1.575 | AI11: =AF11*0.4+AF11 -> 1.876 | AJ11: =1-AF11/Z11 -> 0.23428571
B12: simple | C12: 8594 | D12: SAPOLIO CLEAM CLEANER SOFTSCRUB sa-44 - 8594 | E12: 1 | F12: 0 | G12: visible | H12: SAPOLIO CLEAM CLEANER SOFTSCRUB - 8594 | I12: Softsoap Aquarium Series combines enchanting designs from the sea with Antibacterial liquid soap. It contains germ fighting ingredient to provide strong antibacterial protection. Like other Softsoap products, Softsoap Aquarium Series liquid soap contains light moisturizers to help leave your hands clean and soft. | N12: 1 | O12: 1000 | Z12: 2.35 | AA12: cleaning supplies | AB12: https://fantasydiscountwholesale.com/wp-content/uploads/2023/10/8594-1.jpeg | AC12: 1-2 | AD12: 12 | AE12: =AD12 -> 12 | AF12: 1.79 | AG12: =AF12*0.25+AF12 -> 2.2375 | AH12: =Z12*0.1-Z12 -> -2.115 | AI12: =AF12*0.3+AF12 -> 2.327 | AJ12: =1-AF12/Z12 -> 0.23829787
B13: simple | C13: 7532 | D13: Sapolio POWDER CLEANER Multi purpose sa-45 - 7532 12/450ML | E13: 1 | F13: 0 | G13: visible | H13: Sapolio POWDER CLEANER Multi purpose - 7532 12/450ML | I13: Energizing Hair Styling Gel for Extreme Long Lasting Hold, Gorilla Snot Gel is Ultimate Hair Gel to Energize any Hairstyle | N13: 1 | O13: 1000 | Z13: 1.39 | AA13: cleaning supplies | AB13: https://fantasydiscountwholesale.com/wp-content/uploads/2023/10/7532.jpeg | AC13: 1-2 | AD13: 12 | AE13: =AD13 -> 12 | AF13: 1.04 | AG13: =AF13*0.25+AF13 -> 1.3 | AH13: =Z13*0.1-Z13 -> -1.251 | AI13: =AF13*0.3+AF13 -> 1.352 | AJ13: =1-AF13/Z13 -> 0.25179856
B14: simple | C14: 9300 | D14: Sapolio 650 ml limpia vidrios lavanda sa-41 - 9300 | E14: 1 | F14: 0 | G14: visible | H14: Sapolio 650 ml limpia vidrios lavanda | I14: Sapolio Glass Cleaner Lavender (650ml) delivers a streak-free shine while leaving a pleasant lavender scent. Its powerful formula removes dust, fingerprints, and smudges with ease. Perfect for windows, mirrors, and glass surfaces. Ideal for wholesale and discount stores. | N14: 1 | O14: 1000 | Z14: 1.75 | AA14: cleaning supplies | AB14: https://fantasydiscountwholesale.com/wp-content/uploads/2025/02/9300.jpeg | AC14: 1-2 | AD14: 12 | AE14: =AD14 -> 12 | AF14: 1.35 | AG14: =AF14*0.25+AF14 -> 1.6875 | AH14: =Z14*0.1-Z14 -> -1.575 | AI14: =AF14*0.3+AF14 -> 1.755 | AJ14: =1-AF14/Z14 -> 0.22857143
B15: simple | C15: 7348 | D15: Sapolio Dish Liquid Lemon 17 Oz sa-34 - 7348 | E15: 1 | F15: 0 | G15: visible | H15: Sapolio Dish Liquid Lemon 17 Oz - 7348 | I15: Energizing Hair Styling Gel for Extreme Long Lasting Hold, Gorilla Snot Gel is Ultimate Hair Gel to Energize any Hairstyle | N15: 1 | O15: 1000 | Z15: 1.39 | AA15: cleaning supplies | AB15: https://fantasydiscountwholesale.com/wp-content/uploads/2023/10/7348.jpeg | AC15: 1-3 | AD15: 12 | AE15: =AD15 -> 12 | AF15: 1.04 | AG15: =AF15*0.25+AF15 -> 1.3 | AH15: =Z15*0.1-Z15 -> -1.251 | AI15: =AF15*0.3+AF15 -> 1.352 | AJ15: =1-AF15/Z15 -> 0.25179856
B16: simple | C16: 7355 | D16: Sapolio liquid Dish Soap Apple sa-35 - 7355 | E16: 1 | F16: 0 | G16: visible | H16: Sapolio liquid Dish Soap Apple - 7355 | I16: Energizing Hair Styling Gel for Extreme Long Lasting Hold, Gorilla Snot Gel is Ultimate Hair Gel to Energize any Hairstyle | N16: 1 | O16: 1000 | Z16: 1.39 | AA16: cleaning supplies | AB16: https://fantasydiscountwholesale.com/wp-content/uploads/2023/10/7355-1.jpeg | AC16: 1-3 | AD16: 12 | AE16: =AD16 -> 12 | AF16: 1.04 | AG16: =AF16*0.25+AF16 -> 1.3 | AH16: =Z16*0.1-Z16 -> -1.251 | AI16: =AF16*0.3+AF16 -> 1.352 | AJ16: =1-AF16/Z16 -> 0.25179856
B17: simple | C17: 0361 | D17: Aval jabon lavanda sa-27 400ml - 0361 | E17: 1 | F17: 0 | G17: visible | H17: Aval jabon lavanda 400ml | I17: Aval Rosas Liquid Soap (400ml) offers a gentle yet effective cleanse with a pleasant rose fragrance. Its moisturizing formula leaves hands soft and refreshed. Ideal for daily use in homes or businesses. Great for wholesale and discount stores. | N17: 1 | O17: 1000 | Z17: 1.45 | AA17: Beauty & Personal Care | AB17: https://fantasydiscountwholesale.com/wp-content/uploads/2025/02/8891.jpeg | AC17: 1-3 | AD17: 12 | AE17: =AD17 -> 12 | AF17: 1.09 | AG17: =AF17*0.3+AF17 -> 1.417 | AH17: =Z17*0.1-Z17 -> -1.305 | AI17: =AF17*0.3+AF17 -> 1.417 | AJ17: =1-AF17/Z17 -> 0.24827586
B18: simple | C18: 8914 | D18: Aval jabon rosas sa-28 400ml - 8914 | E18: 1 | F18: 0 | G18: visible | H18: Aval jabon rosas 400ml | I18: Aval Rosas Liquid Soap (400ml) provides a deep yet gentle cleanse with a delightful rose scent. Its moisturizing formula keeps hands soft and fresh. Perfect for everyday use in homes or businesses. Ideal for wholesale and discount stores. | N18: 1 | O18: 1000 | Z18: 1.45 | AA18: Beauty & Personal Care | AB18: https://fantasydiscountwholesale.com/wp-content/uploads/2025/02/8914.jpeg | AC18: 1-3 | AD18: 12 | AE18: =AD18 -> 12 | AF18: 1.09 | AG18: =AF18*0.3+AF18 -> 1.417 | AH18: =Z18*0.1-Z18 -> -1.305 | AI18: =AF18*0.4+AF18 -> 1.526 | AJ18: =1-AF18/Z18 -> 0.24827586
B19: simple | C19: 3543 | D19: Lavavajilla pasta naranja 360g - 3543 - sa-33 | E19: 1 | F19: 0 | G19: visible | H19: Lavavajilla pasta naranja 360g | I19: Orange-Scented Dishwashing Paste (360g) cuts through grease and tough stains with ease. Its concentrated formula ensures long-lasting use, leaving dishes sparkling clean with a fresh citrus scent. Ideal for households and businesses. Perfect for wholesale and discount stores. | N19: 1 | O19: 1000 | Z19: 1.59 | AA19: cleaning supplies | AB19: https://fantasydiscountwholesale.com/wp-content/uploads/2025/02/3543.jpeg | AC19: 1-3 | AD19: 12 | AE19: =AD19 -> 12 | AF19: 1.16 | AG19: =AF19*0.25+AF19 -> 1.45 | AH19: =Z19*0.1-Z19 -> -1.431 | AI19: =AF19*0.3+AF19 -> 1.508 | AJ19: =1-AF19/Z19 -> 0.27044025
B20: simple | C20: 7729 | D20: Lavavajilla pasta limon 330g - 7729 - sa-30 | E20: 1 | F20: 0 | G20: visible | H20: Lavavajilla pasta limon 330g | I20: Lemon-Scented Dishwashing Paste (330g) effectively removes grease and tough stains while leaving a refreshing citrus scent. Its concentrated formula ensures long-lasting use and sparkling clean dishes. Ideal for households and businesses. Perfect for wholesale and discount stores. | N20: 1 | O20: 1000 | Z20: 1.39 | AA20: cleaning supplies | AB20: https://fantasydiscountwholesale.com/wp-content/uploads/2025/02/7729.jpeg | AC20: 1-3 | AD20: 12 | AE20: =AD20 -> 12 | AF20: 1.04 | AG20: 1.3 | AH20: =Z20*0.1-Z20 -> -1.251 | AI20: =AF20*0.4+AF20 -> 1.456 | AJ20: =1-AF20/Z20 -> 0.25179856
B21: simple | C21: 6026 | D21: Sapolio Air freshner Anti-tabacco sa-17 - 6026 | E21: 1 | F21: 0 | G21: visible | H21: Sapolio Air freshner Anti-tabacco - 6026 | I21: Energizing Hair Styling Gel for Extreme Long Lasting Hold, Gorilla Snot Gel is Ultimate Hair Gel to Energize any Hairstyle | N21: 1 | O21: 1000 | Z21: 1.9 | AA21: Air Freshener | AB21: https://fantasydiscountwholesale.com/wp-content/uploads/2023/10/6026.jpeg | AC21: 1-4 | AD21: 12 | AE21: =AD21 -> 12 | AF21: 1.46 | AG21: =AF21*0.25+AF21 -> 1.825 | AH21: =Z21*0.1-Z21 -> -1.71 | AI21: =AF21*0.4+AF21 -> 2.044 | AJ21: =1-AF21/Z21 -> 0.23157895
B22: simple | C22: 8208 | D22: SAPOLIO 550 ML . STAIN REMOVER ROPA COLOR sa-08 - 8208 | E22: 1 | F22: 0 | G22: visible | H22: SAPOLIO STAIN REMOVER ROPA COLOR 550ML - 8208 | I22: Energizing Hair Styling Gel for Extreme Long Lasting Hold, Gorilla Snot Gel is Ultimate Hair Gel to Energize any Hairstyle | N22: 1 | O22: 1000 | Z22: 1.39 | AA22: cleaning supplies | AB22: https://fantasydiscountwholesale.com/wp-content/uploads/2023/10/8208.jpeg | AC22: 1-4 | AD22: 12 | AE22: =AD22 -> 12 | AF22: 1.05 | AG22: =AF22*0.28+AF22 -> 1.344 | AH22: =Z22*0.1-Z22 -> -1.251 | AI22: =AF22*0.4+AF22 -> 1.47 | AJ22: =1-AF22/Z22 -> 0.24460432
B23: simple | C23: 7712 | D23: Lavavajilla pasta limon 200g sa-32 - 7712 | E23: 1 | F23: 0 | G23: visible | H23: Lavavajilla pasta limon 200g | I23: Lemon-Scented Dishwashing Paste (200g) powerfully cuts through grease and tough stains, leaving dishes spotless with a fresh citrus scent. Its concentrated formula ensures long-lasting use. Ideal for households and businesses. Perfect for wholesale and discount stores. | N23: 1 | O23: 1000 | Z23: 0.75 | AA23: cleaning supplies | AB23: https://fantasydiscountwholesale.com/wp-content/uploads/2025/02/7712.jpeg | AC23: 1-4 | AD23: 24 | AE23: =AD23 -> 24 | AF23: 0.58 | AG23: =AF23*0.25+AF23 -> 0.725 | AH23: =Z23*0.1-Z23 -> -0.675 | AI23: =AF23*0.4+AF23 -> 0.812 | AJ23: =1-AF23/Z23 -> 0.22666667
B24: simple | C24: 6088 | D24: Sapolio air freshner Bebe Arrullo - 6088 SA-25 | E24: 1 | F24: 0 | G24: visible | H24: Sapolio air freshner Bebe Arrullo - 6088 SA-25 | I24: Sapolio Baby Lullaby Air Freshener – SA‑25: gentle-scent spray neutralizes odors and fills rooms with a soft, comforting baby powder fragrance. Ideal for bulk wholesale to retailers, nurseries, and hospitality. | N24: 1 | O24: 1000 | Z24: 1.9 | AA24: Air Freshener | AB24: https://fantasydiscountwholesale.com/wp-content/uploads/2025/06/6088.jpg | AC24: 1-4 | AD24: 12 | AE24: =AD24 -> 12 | AF24: 1.46 | AG24: =AF24*0.25+AF24 -> 1.825 | AH24: =Z24*0.1-Z24 -> -1.71 | AI24: =AF24*0.4+AF24 -> 2.044 | AJ24: =1-AF24/Z24 -> 0.23157895
B25: simple | C25: 5218 | D25: Sapolio Air freshner Apple Cinnamon sa-20 - 5218 | E25: 1 | F25: 0 | G25: visible | H25: Sapolio Air freshner Apple Cinnamon - 5218 | I25: Softsoap Aquarium Series combines enchanting designs from the sea with Antibacterial liquid soap. It contains germ fighting ingredient to provide strong antibacterial protection. Like other Softsoap products, Softsoap Aquarium Series liquid soap contains light moisturizers to help leave your hands clean and soft. | N25: 1 | O25: 1000 | Z25: 1.9 | AA25: Air Freshener | AB25: https://fantasydiscountwholesale.com/wp-content/uploads/2023/10/5218.jpeg | AC25: 1-5 | AD25: 12 | AE25: =AD25 -> 12 | AF25: 1.46 | AG25: =AF25*0.25+AF25 -> 1.825 | AH25: =Z25*0.1-Z25 -> -1.71 | AI25: =AF25*0.4+AF25 -> 2.044 | AJ25: =1-AF25/Z25 -> 0.23157895
B26: simple | C26: 5999 | D26: Sapolio Air freshner Potpourri sa-18 - 5999 | E26: 1 | F26: 0 | G26: visible | H26: Sapolio Air freshner Potpourri - 5999 | I26: Softsoap Aquarium Series combines enchanting designs from the sea with Antibacterial liquid soap. It contains germ fighting ingredient to provide strong antibacterial protection. Like other Softsoap products, Softsoap Aquarium Series liquid soap contains light moisturizers to help leave your hands clean and soft. | N26: 1 | O26: 1000 | Z26: 1.9 | AA26: Air Freshener | AB26: https://fantasydiscountwholesale.com/wp-content/uploads/2023/10/5999.jpeg | AC26: 1-5 | AD26: 12 | AE26: =AD26 -> 12 | AF26: 1.46 | AG26: =AF26*0.25+AF26 -> 1.825 | AH26: =Z26*0.1-Z26 -> -1.71 | AI26: =AF26*0.4+AF26 -> 2.044 | AJ26: =1-AF26/Z26 -> 0.23157895
B27: simple | C27: 9637 | D27: Perfumatic Sapolio Refill French Vanilla - 9637 | E27: 0 | F27: 0 | G27: hidden | H27: Perfumatic Sapolio Refill French Vanilla - 9637 | I27: Softsoap Aquarium Series combines enchanting designs from the sea with Antibacterial liquid soap. It contains germ fighting ingredient to provide strong antibacterial protection. Like other Softsoap products, Softsoap Aquarium Series liquid soap contains light moisturizers to help leave your hands clean and soft. | N27: 0 | O27: 0 | Z27: 2.29 | AA27: Air Freshener | AB27: https://fantasydiscountwholesale.com/wp-content/uploads/2023/10/9637.jpeg | AC27: 1-5 | AD27: 12 | AE27: =AD27 -> 12 | AF27: 1.82 | AG27: =AF27*0.25+AF27 -> 2.275 | AH27: =Z27*0.1-Z27 -> -2.061 | AI27: =AF27*0.4+AF27 -> 2.548 | AJ27: =1-AF27/Z27 -> 0.20524017
B28: simple | C28: 5982 | D28: Sapolio Air freshner Lavander sa-23 - 5982 | E28: 1 | F28: 0 | G28: visible | H28: Sapolio Air freshner Lavander - 5982 | I28: Energizing Hair Styling Gel for Extreme Long Lasting Hold, Gorilla Snot Gel is Ultimate Hair Gel to Energize any Hairstyle | N28: 1 | O28: 1000 | Z28: 1.9 | AA28: Air Freshener | AB28: https://fantasydiscountwholesale.com/wp-content/uploads/2023/10/5982.jpeg | AC28: 1-5 | AD28: 12 | AE28: =AD28 -> 12 | AF28: 1.46 | AG28: =AF28*0.25+AF28 -> 1.825 | AH28: =Z28*0.1-Z28 -> -1.71 | AI28: =AF28*0.4+AF28 -> 2.044 | AJ28: =1-AF28/Z28 -> 0.23157895
B29: simple | C29: 6853 | D29: Sapolio Air freshner Melon sa-24 - 6853 | E29: 1 | F29: 0 | G29: visible | H29: Sapolio Air freshner Melon - 6853 | I29: Energizing Hair Styling Gel for Extreme Long Lasting Hold, Gorilla Snot Gel is Ultimate Hair Gel to Energize any Hairstyle | N29: 1 | O29: 1000 | Z29: 1.9 | AA29: Air Freshener | AB29: https://fantasydiscountwholesale.com/wp-content/uploads/2023/10/6853.jpeg | AC29: 1-5 | AD29: 12 | AE29: =AD29 -> 12 | AF29: 1.46 | AG29: =AF29*0.25+AF29 -> 1.825 | AH29: =Z29*0.1-Z29 -> -1.71 | AI29: =AF29*0.4+AF29 -> 2.044 | AJ29: =1-AF29/Z29 -> 0.23157895
B30: simple | C30: 6002 | D30: Sapolio Air freshner Rose sa-19 - 6002 | E30: 1 | F30: 0 | G30: visible | H30: Sapolio Air freshner Rose - 6002 | I30: Energizing Hair Styling Gel for Extreme Long Lasting Hold, Gorilla Snot Gel is Ultimate Hair Gel to Energize any Hairstyle | N30: 1 | O30: 1000 | Z30: 1.9 | AA30: Air Freshener | AB30: https://fantasydiscountwholesale.com/wp-content/uploads/2023/10/6002.jpeg | AC30: 1-5 | AD30: 12 | AE30: =AD30 -> 12 | AF30: 1.46 | AG30: =AF30*0.25+AF30 -> 1.825 | AH30: =Z30*0.1-Z30 -> -1.71 | AI30: =AF30*0.4+AF30 -> 2.044 | AJ30: =1-AF30/Z30 -> 0.23157895
B31: simple | C31: 3260 | D31: Sapolio Air freshner Vanilla sa-22 - 3260 | E31: 1 | F31: 0 | G31: visible | H31: Sapolio Air freshner Vanilla - 3260 | I31: Energizing Hair Styling Gel for Extreme Long Lasting Hold, Gorilla Snot Gel is Ultimate Hair Gel to Energize any Hairstyle | N31: 1 | O31: 1000 | Z31: 1.9 | AA31: Air Freshener | AB31: https://fantasydiscountwholesale.com/wp-content/uploads/2023/10/3260.jpeg | AC31: 1-5 | AD31: 12 | AE31: =AD31 -> 12 | AF31: 1.46 | AG31: =AF31*0.25+AF31 -> 1.825 | AH31: =Z31*0.1-Z31 -> -1.71 | AI31: =AF31*0.4+AF31 -> 2.044 | AJ31: =1-AF31/Z31 -> 0.23157895
B32: simple | C32: N-211 | D32: NAIL CLIPPER STAINLESS STEEL - N-211 | E32: 1 | F32: 0 | G32: visible | H32: Stainless Steel Nail Clippers | I32: Finger nail clipper and toe nail clipper - MANICURE - PEDICURE - GROOMING – NAIL CARE | N32: 1 | O32: 1000 | Z32: 5.5 | AA32: Miscellaneous | AB32: https://fantasydiscountwholesale.com/wp-content/uploads/2023/10/211-Corta-unas.jpeg | AC32: 1-6 | AD32: 1 | AE32: =AD32 -> 1 | AF32: 1.56 | AG32: =AF32*1.85+AF32 -> 4.446 | AH32: =Z32*0.1-Z32 -> -4.95 | AI32: =AF32*0.4+AF32 -> 2.184 | AJ32: =1-AF32/Z32 -> 0.71636364
B33: simple | C33: 9113 | D33: Sapolio 1800 ML. stain remover color clothes 60 oz - 9113 - sa-10 | E33: 1 | F33: 0 | G33: visible | H33: Stain remover color clothes 60 oz - 9113 | I33: Energizing Hair Styling Gel for Extreme Long Lasting Hold, Gorilla Snot Gel is Ultimate Hair Gel to Energize any Hairstyle | N33: 1 | O33: 1000 | Z33: 3.89 | AA33: cleaning supplies | AB33: https://fantasydiscountwholesale.com/wp-content/uploads/2023/10/9113.jpeg | AC33: 1-6 | AD33: 6 | AE33: =AD33 -> 6 | AF33: 2.99 | AG33: =AF33*0.259+AF33 -> 3.76441 | AH33: =Z33*0.1-Z33 -> -3.501 | AI33: =AF33*0.4+AF33 -> 4.186 | AJ33: =1-AF33/Z33 -> 0.23136247
B34: simple | C34: 9991 | D34: SAPOLIO 930 ML . STAIN REMOVER ROPA COLOR sa-09 - 89991 | E34: 1 | F34: 0 | G34: visible | H34: SAPOLIO 930 ML . STAIN REMOVER ROPA COLOR - 89991 | I34: Sapolio Stain Remover for Colored Clothes (930ml) effectively removes tough stains while protecting fabric colors. Its powerful formula lifts dirt and grime without fading. Ideal for maintaining vibrant clothing. Perfect for wholesale and discount stores. | N34: 1 | O34: 1000 | Z34: 1.85 | AA34: cleaning supplies | AB34: https://fantasydiscountwholesale.com/wp-content/uploads/2025/02/9991.jpeg | AC34: 1-6 | AD34: 12 | AE34: =AD34 -> 12 | AF34: 1.42 | AG34: =AF34*0.25+AF34 -> 1.775 | AH34: =Z34*0.1-Z34 -> -1.665 | AI34: =AF34*0.4+AF34 -> 1.988 | AJ34: =1-AF34/Z34 -> 0.23243243
B35: simple | C35: FD083 | D35: Boli Comb Hair brush - FD083 | E35: 1 | F35: 0 | G35: visible | H35: Boli Comb Hair brush - FD083 | I35: Discover the perfect hairbrush for your daily haircare routine. Our Hair Brush is designed with your comfort and hair health in mind. Its gentle yet effective bristles effortlessly detangle and smooth your locks, reducing breakage and promoting a healthy shine. The ergonomic handle ensures a comfortable grip, making styling and brushing a breeze. Upgrade your haircare essentials and achieve the beautiful, well-groomed hair you deserve with our Hair Brush. Elevate your daily routine and enjoy a healthier, more manageable mane. Get yours today for tangle-free, gorgeous hair! 💇‍♀️✨🌟 | N35: 1 | O35: 1000 | Z35: 1.1 | AA35: Beauty & Personal Care | AB35: https://fantasydiscountwholesale.com/wp-content/uploads/2023/10/FD083-1.jpeg ,https://fantasydiscountwholesale.com/wp-content/uploads/2023/10/FD083.jpeg | AC35: 2-1 | AD35: 12 | AE35: =AD35 -> 12 | AF35: 0.5 | AG35: =AF35*0.5+AF35 -> 0.75 | AH35: =Z35*0.1-Z35 -> -0.99 | AI35: =AF35*0.4+AF35 -> 0.7 | AJ35: =1-AF35/Z35 -> 0.54545455
B36: simple | C36: JW-04 | D36: Suction cups - JW-04 | E36: 1 | F36: 0 | G36: visible | H36: Transparant, waterproof, PVC suction cup with metal hook. | I36: Can be used on any smooth surface, such as glass, a window, a wall etc. Suitable for the kitchen, the bathroom, the office as well as toy accessories. Easy to install and tear off, without any damage to the surface. There is a small hook that can be used to hang items with. | N36: 1 | O36: 1000 | Z36: 1 | AA36: Bathroom | AB36: https://fantasydiscountwholesale.com/wp-content/uploads/2023/10/JW-04-1.jpeg | AC36: 2-1 | AD36: 12 | AE36: =AD36 -> 12 | AF36: 0.44 | AG36: =AF36*0.8+AF36 -> 0.792 | AH36: =Z36*0.1-Z36 -> -0.9 | AI36: =AF36*0.4+AF36 -> 0.616 | AJ36: =1-AF36/Z36 -> 0.56
B37: simple | C37: FD913 | D37: Sink Screens Strainers 3PC STRAINNER 5CM,7CM,11CM - FD913 | E37: 1 | F37: 0 | G37: visible | H37: Sink Screens Strainers 3PC STRAINNER 5CM,7CM,11CM | I37: Offer your customers the ultimate solution in kitchen convenience with our Sink Screens Strainers 3-Piece Set. This set includes strainers in three practical sizes - 5cm, 7cm, and 11cm - to suit a variety of sink dimensions and needs. These strainers effectively prevent food particles and debris from clogging drains while allowing water to flow freely. Their versatile sizes make them perfect for kitchen sinks, bathroom basins, and utility sinks. Easy to clean and maintain, these strainers are essential for any household. Stock up on this indispensable set for a hassle-free, efficient kitchen experience. | N37: 1 | O37: 1000 | Z37: 0.75 | AA37: Kitchen | AB37: https://fantasydiscountwholesale.com/wp-content/uploads/2023/10/FD913-1.jpeg | AC37: 2-2 | AD37: 12 | AE37: =AD37 -> 12 | AF37: 0.33 | AG37: =AF37*0.83+AF37 -> 0.6039 | AH37: =Z37*0.1-Z37 -> -0.675 | AI37: =AF37*0.4+AF37 -> 0.462 | AJ37: =1-AF37/Z37 -> 0.56
B38: simple | C38: CH87337 | D38: 2PCS Prong Adapter - CH87337 | E38: 1 | F38: 0 | G38: visible | H38: 2PCS Prong Adapter - CH87337 | I38: 2PCS Prong Adapter – CH87337: Converts 2-prong outlets to 3-prong, providing grounding for added safety. Compact and easy to use. Ideal for wholesale to hardware and electrical supply retailers. | N38: 1 | O38: 1000 | Z38: 1.39 | AA38: Tools | AB38: https://fantasydiscountwholesale.com/wp-content/uploads/2025/06/CH87337.jpg | AC38: 2-2 | AD38: 6 | AE38: =AD38 -> 6 | AF38: 0.87 | AG38: =AF38*0.4+AF38 -> 1.218 | AH38: =Z38*0.1-Z38 -> -1.251 | AI38: =AF38*0.4+AF38 -> 1.218 | AJ38: =1-AF38/Z38 -> 0.37410072
B39: simple | C39: IN81752 | D39: 250CT 2PK Medium Matches - IN81752 | E39: 1 | F39: 0 | G39: visible | H39: 250CT 2PK Medium Matches - IN81752 | I39: 250CT 2PK Medium Matches – IN81752: Each pack includes two boxes of 250 wooden matches, totaling 500 matches. Designed for easy strike-on-box ignition, they're ideal for lighting candles, stoves, grills, and campfires. Perfect for wholesale to hardware, camping, and general merchandise retailers. | N39: 1 | O39: 1000 | Z39: 0.79 | AA39: Kitchen | AB39: https://fantasydiscountwholesale.com/wp-content/uploads/2025/06/IN81752.jpg | AC39: 2-2 | AD39: 12 | AE39: =AD39 -> 12 | AF39: 0.51 | AG39: =AF39*0.4+AF39 -> 0.714 | AH39: =Z39*0.1-Z39 -> -0.711 | AI39: =AF39*0.4+AF39 -> 0.714 | AJ39: =1-AF39/Z39 -> 0.35443038
B40: simple | C40: IN81751 | D40: 32CT 10PK Wooden Matches- IN81751 | E40: 1 | F40: 0 | G40: visible | H40: 32CT 10PK Wooden Matches- IN81751 | I40: 32CT 10PK Wooden Pocket Matches – IN81751: Each pack contains 10 boxes of 32 wooden matches, totaling 320 matches. Strike-on-box design ensures easy ignition. Ideal for wholesale to hardware, camping, and general merchandise retailers. | N40: 1 | O40: 1000 | Z40: 0.49 | AA40: Kitchen | AB40: https://fantasydiscountwholesale.com/wp-content/uploads/2025/06/IN81751.jpg | AC40: 2-2 | AD40: 12 | AE40: =AD40 -> 12 | AF40: 0.27 | AG40: =AF40*0.58+AF40 -> 0.4266 | AH40: =Z40*0.1-Z40 -> -0.441 | AI40: =AF40*0.4+AF40 -> 0.378 | AJ40: =1-AF40/Z40 -> 0.44897959
B41: simple | C41: IN81750-A | D41: 11" 40CT 1PK BBQ/ Fire Place Matches - IN81750-A | E41: 0 | F41: 0 | G41: hidden | H41: 11" 40CT 1PK BBQ/ Fire Place Matches - IN81750-A | I41: 11" 40CT 1PK BBQ/Fireplace Matches – IN81750-A: Long wooden matches designed for safely lighting fireplaces, grills, and candles. Each box contains 40 matches. Ideal for wholesale to hardware, camping, and general merchandise retailers. | N41: 0 | O41: 0 | Z41: 0.9 | AA41: Kitchen | AB41: https://fantasydiscountwholesale.com/wp-content/uploads/2025/06/IN81750-A.jpg | AC41: 2-2 | AD41: 12 | AE41: =AD41 -> 12 | AF41: 0.6 | AG41: =AF41*0.4+AF41 -> 0.84 | AH41: =Z41*0.1-Z41 -> -0.81 | AI41: =AF41*0.4+AF41 -> 0.84 | AJ41: =1-AF41/Z41 -> 0.33333333
B42: simple | C42: CH80088 | D42: Cotton Twine / soga tamal - CH80088 | E42: 1 | F42: 0 | G42: visible | H42: 230FT 2PC Cotton Twine - CH80088 | I42: 230FT 2PC Cotton Twine – CH80088: Set of two 100% natural cotton twine rolls, each 115 feet long. Ideal for cooking, crafts, gardening, and gift wrapping. Perfect for wholesale to kitchenware, craft, and general merchandise retailers. | N42: 1 | O42: 1000 | Z42: 0.65 | AA42: Kitchen | AB42: https://fantasydiscountwholesale.com/wp-content/uploads/2025/06/CH80088.jpg | AC42: 2-2 | AD42: 12 | AE42: =AD42 -> 12 | AF42: 0.42 | AG42: =AF42*0.4+AF42 -> 0.588 | AH42: =Z42*0.1-Z42 -> -0.585 | AI42: =AF42*0.4+AF42 -> 0.588 | AJ42: =1-AF42/Z42 -> 0.35384615
B43: simple | C43: FD426 | D43: Agujas de maquina / Knitting parts- FD426 | E43: 1 | F43: 0 | G43: visible | H43: Universal Sewing Machine Needles | I43: El paquete incluye 10 agujas universales de tamaño 90/14 que se pueden utilizar en muchas otras máquinas como Brother y otras máquinas de coser de alta calidad. Las agujas de máquina de coser Singer de tamaño universal 90/14 están diseñadas para coser telas tejidas de peso medio. | N43: 1 | O43: 1000 | Z43: 0.69 | AA43: Sewing | AB43: https://fantasydiscountwholesale.com/wp-content/uploads/2023/10/FD-426-1.jpeg | AC43: 2-3 | AD43: 12 | AE43: =AD43 -> 12 | AF43: 0.35 | AG43: =AF43*0.7+AF43 -> 0.595 | AH43: =Z43*0.1-Z43 -> -0.621 | AI43: =AF43*0.4+AF43 -> 0.49 | AJ43: =1-AF43/Z43 -> 0.49275362
B44: simple | C44: 502831 | D44: Comb for men - 502831 | E44: 0 | F44: 0 | G44: hidden | H44: two color comb for men 6pc | I44: Introducing our Two-Color Comb Set for Men, featuring six stylish combs in complementary shades. With a sleek design and durable construction, these combs are perfect for grooming and styling your hair with precision and ease. Elevate your grooming routine with this versatile set, perfect for everyday use or travel. | N44: 0 | O44: 0 | Z44: 0.79 | AA44: Accessory | AB44: https://fantasydiscountwholesale.com/wp-content/uploads/2024/03/502831.jpeg | AC44: 2-3 | AD44: 6 | AE44: =AD44 -> 6 | AF44: 0.52 | AG44: =AF44*0.4+AF44 -> 0.728 | AH44: =Z44*0.1-Z44 -> -0.711 | AI44: =AF44*0.4+AF44 -> 0.728 | AJ44: =1-AF44/Z44 -> 0.34177215
B45: simple | C45: CH87333 | D45: 03 Outlets Adapter W/ Sensor Light - CH87333 | E45: 1 | F45: 0 | G45: visible | H45: 03 Outlets Adapter W/ Sensor Light - CH87333 | I45: 3-Outlet Adapter with Sensor Night Light – CH87333: Expands one outlet into three, featuring a built-in sensor night light that activates in low light. Ideal for wholesale to hardware and home goods retailers. | N45: 1 | O45: 1000 | Z45: 1.49 | AA45: Tools | AB45: https://fantasydiscountwholesale.com/wp-content/uploads/2025/06/CH87333.jpg | AC45: 2-3 | AD45: 6 | AE45: =AD45 -> 6 | AF45: 0.98 | AG45: =AF45*0.4+AF45 -> 1.372 | AH45: =Z45*0.1-Z45 -> -1.341 | AI45: =AF45*0.4+AF45 -> 1.372 | AJ45: =1-AF45/Z45 -> 0.34228188
B46: simple | C46: CH87335 | D46: 03 Outlets Heavy Duty Adapter - CH87335 | E46: 1 | F46: 0 | G46: visible | H46: 03 Outlets Heavy Duty Adapter - CH87335 | I46: 03 Outlets Heavy Duty Adapter – CH87335: Converts one grounded outlet into three, supporting up to 15A/125V. Durable PVC construction ensures longevity. Ideal for wholesale to hardware and electrical supply retailers | N46: 1 | O46: 1000 | Z46: 2 | AA46: Tools | AB46: https://fantasydiscountwholesale.com/wp-content/uploads/2025/06/CH87335.jpg | AC46: 2-3 | AD46: 6 | AE46: =AD46 -> 6 | AF46: 1.33 | AG46: =AF46*0.4+AF46 -> 1.862 | AH46: =Z46*0.1-Z46 -> -1.8 | AI46: =AF46*0.4+AF46 -> 1.862 | AJ46: =1-AF46/Z46 -> 0.335
B47: simple | C47: CH87336 | D47: 06 Outlets Grounding Adapter - CH87336 | E47: 0 | F47: 0 | G47: hidden | H47: 06 Outlets Grounding Adapter - CH87336 | I47: 6-Outlet Grounding Adapter – CH87: Expands a single outlet into six grounded outlets. Supports up to 15A/125V, ideal for powering multiple devices. Perfect for wholesale to hardware and electrical supply retailers. | N47: 0 | O47: 0 | Z47: 2.45 | AA47: Tools | AB47: https://fantasydiscountwholesale.com/wp-content/uploads/2025/06/CH87.jpg | AC47: 2-3 | AD47: 6 | AE47: =AD47 -> 6 | AF47: 1.63 | AG47: =AF47*0.4+AF47 -> 2.282 | AH47: =Z47*0.1-Z47 -> -2.205 | AI47: =AF47*0.4+AF47 -> 2.282 | AJ47: =1-AF47/Z47 -> 0.33469388
B48: simple | C48: CH48111 | D48: Extension 2FT / 6 Outlets Power Strip - CH48111 | E48: 1 | F48: 0 | G48: visible | H48: 2FT / 6 Outlets Power Strip - CH48111 | I48: 2FT 6-Outlet Power Strip – CH48111: Compact power strip with six grounded outlets and a 2-foot heavy-duty cord. Ideal for home, office, or workshop use. Perfect for wholesale to hardware and electrical supply retailers. | N48: 1 | O48: 1000 | Z48: 5.05 | AA48: Tools | AB48: https://fantasydiscountwholesale.com/wp-content/uploads/2025/06/CH48111.jpg | AC48: 2-3 | AD48: 6 | AE48: =AD48 -> 6 | AF48: 3.36 | AG48: =AF48*0.4+AF48 -> 4.704 | AH48: =Z48*0.1-Z48 -> -4.545 | AI48: =AF48*0.4+AF48 -> 4.704 | AJ48: =1-AF48/Z48 -> 0.33465347
B49: simple | C49: 50073 | D49: Microwave cover - 50073 | E49: 0 | F49: 0 | G49: hidden | H49: Microwave cover | I49: Microwave Food Cover: with holder space to grab the cover is splatter guard cover, not only keeps your microwave clean, but also can prevent burns. You can immediately take your food out of the microwave or oven after heating without wasting any of your time waiting. | N49: 0 | O49: 0 | Z49: 0.85 | AA49: Kitchen | AB49: https://fantasydiscountwholesale.com/wp-content/uploads/2023/10/50073.jpeg | AC49: 2-4 | AD49: 12 | AE49: =AD49 -> 12 | AF49: 0.54 | AG49: =AF49*0.4+AF49 -> 0.756 | AH49: =Z49*0.1-Z49 -> -0.765 | AI49: =AF49*0.4+AF49 -> 0.756 | AJ49: =1-AF49/Z49 -> 0.36470588
B50: simple | C50: 5726 | D50: Desodorante Feelin Fresh / Feelin fresh Deodorant - 5726 | E50: 0 | F50: 0 | G50: hidden | H50: Desodorante Feelin Fresh / Feelin fresh Deodorant - 5726 | I50: Energizing Hair Styling Gel for Extreme Long Lasting Hold, Gorilla Snot Gel is Ultimate Hair Gel to Energize any Hairstyle | N50: 0 | O50: 0 | Z50: 1.05 | AA50: Beauty & Personal Care | AB50: https://fantasydiscountwholesale.com/wp-content/uploads/2023/10/5726.jpeg | AC50: 2-4 | AD50: 12 | AE50: =AD50 -> 12 | AF50: 0.7 | AG50: =AF50*0.4+AF50 -> 0.98 | AH50: =Z50*0.1-Z50 -> -0.945 | AI50: =AF50*0.4+AF50 -> 0.98 | AJ50: =1-AF50/Z50 -> 0.33333333
B51: simple | C51: 5028 | D51: Plastic apron mix - 5028 | E51: 1 | F51: 0 | G51: visible | H51: Plastic apron mix styles | I51: Stay clean and stylish with our plastic aprons in assorted designs. Perfect for cooking, crafting, and more, these durable aprons offer excellent protection against spills and stains. Easy to clean and comfortable to wear, they add a fun touch to any activity. | N51: 1 | O51: 1000 | Z51: 1.95 | AA51: Kitchen | AB51: https://fantasydiscountwholesale.com/wp-content/uploads/2023/10/FD701-scaled.jpeg | AC51: 2-4 | AD51: 6 | AE51: =AD51 -> 6 | AF51: 1.07 | AG51: =AF51*0.632+AF51 -> 1.74624 | AH51: =Z51*0.1-Z51 -> -1.755 | AI51: =AF51*0.4+AF51 -> 1.498 | AJ51: =1-AF51/Z51 -> 0.45128205
B52: simple | C52: 4984 | D52: Microwave cover - 4984 | E52: 0 | F52: 0 | G52: hidden | H52: Microwave cover - 4984 | I52: Microwave Cover, model 4984, is designed to prevent splatters and spills while reheating food. Its durable, heat-resistant material fits over most plates and bowls, keeping your microwave clean and reducing mess. Ideal for everyday use, it ensures even heating and helps retain moisture in your food. | N52: 0 | O52: 0 | Z52: 0.99 | AA52: Kitchen | AB52: https://fantasydiscountwholesale.com/wp-content/uploads/2023/10/50073.jpeg | AC52: 2-4 | AD52: 6 | AE52: =AD52 -> 6 | AF52: 0.64 | AG52: =AF52*0.4+AF52 -> 0.896 | AH52: =Z52*0.1-Z52 -> -0.891 | AI52: =AF52*0.4+AF52 -> 0.896 | AJ52: =1-AF52/Z52 -> 0.35353535
B53: simple | C53: 69465 | D53: Avon feeling fresh - 69465 | E53: 1 | F53: 0 | G53: visible | H53: Avon feeling fresh - 69465 | I53: Avon Feeling Fresh – 69465 offers reliable 24-hour odor protection with a clean, refreshing scent. Gentle on skin and quick-drying. Perfect for wholesale to beauty supply stores, pharmacies, and retailers. | N53: 1 | O53: 1000 | Z53: 2.19 | AA53: Beauty & Personal Care | AB53: https://fantasydiscountwholesale.com/wp-content/uploads/2025/05/69465.jpg | AC53: 2-4 | AD53: 12 | AE53: =AD53 -> 12 | AF53: 1.59 | AG53: 2.07 | AH53: =Z53*0.1-Z53 -> -1.971 | AI53: =AF53*0.4+AF53 -> 2.226 | AJ53: =1-AF53/Z53 -> 0.2739726
B54: simple | C54: 69519 | D54: Avon Timeless - 69519 | E54: 0 | F54: 0 | G54: hidden | H54: Avon Timeless - 69519 | I54: Avon Timeless – 69519 is a classic, elegant fragrance with floral and spicy notes, perfect for everyday wear. A nostalgic favorite. Ideal for wholesale to beauty stores, gift shops, and retailers. | N54: 0 | O54: 0 | Z54: 2.19 | AA54: Beauty & Personal Care | AB54: https://fantasydiscountwholesale.com/wp-content/uploads/2025/05/69519.jpg | AC54: 2-4 | AD54: 12 | AE54: =AD54 -> 12 | AF54: 1.59 | AG54: 2.07 | AH54: =Z54*0.1-Z54 -> -1.971 | AI54: =AF54*0.4+AF54 -> 2.226 | AJ54: =1-AF54/Z54 -> 0.2739726
B55: simple | C55: 69463 | D55: Avon onDuty 24hr - 69463 | E55: 1 | F55: 0 | G55: visible | H55: Avon onDuty 24hr - 69463 | I55: Avon OnDuty 24hr – 69463 provides long-lasting deodorant protection with a clean, fresh scent. Quick-drying and gentle on skin. Perfect for wholesale to pharmacies, beauty shops, and personal care retailers. | N55: 1 | O55: 1000 | Z55: 2.19 | AA55: Beauty & Personal Care | AB55: https://fantasydiscountwholesale.com/wp-content/uploads/2025/05/69463.jpg | AC55: 2-4 | AD55: 12 | AE55: =AD55 -> 12 | AF55: 1.59 | AG55: 2.07 | AH55: =Z55*0.1-Z55 -> -1.971 | AI55: =AF55*0.4+AF55 -> 2.226 | AJ55: =1-AF55/Z55 -> 0.2739726
B56: simple | C56: 69506 | D56: Avon Mesmerize - 69506 | E56: 0 | F56: 0 | G56: hidden | H56: Avon Mesmerize - 69506 | I56: Avon Mesmerize – 69506 is a bold, sophisticated fragrance with warm, spicy notes ideal for evening wear. A customer favorite. Perfect for wholesale to perfume shops, gift stores, and retailers. | N56: 0 | O56: 0 | Z56: 2.19 | AA56: Beauty & Personal Care | AB56: https://fantasydiscountwholesale.com/wp-content/uploads/2025/05/69506.jpg | AC56: 2-4 | AD56: 12 | AE56: =AD56 -> 12 | AF56: 1.59 | AG56: 2.07 | AH56: =Z56*0.1-Z56 -> -1.971 | AI56: =AF56*0.4+AF56 -> 2.226 | AJ56: =1-AF56/Z56 -> 0.2739726
B57: simple | C57: 69512 | D57: Avon Imari - 69512 | E57: 1 | F57: 0 | G57: visible | H57: Avon Imari - 69512 | I57: Avon Imari 69512 delivers an oriental floral fragrance blending bergamot, jasmine, patchouli for lasting allure. Recognizable brand boosts shelf appeal and repeat purchases, providing excellent margins for bulk wholesale buyers. | N57: 1 | O57: 1000 | Z57: 2.19 | AA57: Beauty & Personal Care | AB57: https://fantasydiscountwholesale.com/wp-content/uploads/2025/05/69512.jpg | AC57: 2-4 | AD57: 12 | AE57: =AD57 -> 12 | AF57: 1.59 | AG57: 2.07 | AH57: =Z57*0.1-Z57 -> -1.971 | AI57: =AF57*0.4+AF57 -> 2.226 | AJ57: =1-AF57/Z57 -> 0.2739726
B58: simple | C58: 69504 | D58: Avon Sweet honesty - 69504 | E58: 1 | F58: 0 | G58: visible | H58: Avon Sweet honesty - 69504 | I58: Avon Sweet Honesty – 69504 is a light, romantic fragrance with soft floral and powdery notes. A timeless classic. Perfect for wholesale to beauty retailers, gift shops, and fragrance distributors. | N58: 1 | O58: 1000 | Z58: 2.19 | AA58: Beauty & Personal Care | AB58: https://fantasydiscountwholesale.com/wp-content/uploads/2025/05/69504.jpg | AC58: 2-4 | AD58: 12 | AE58: =AD58 -> 12 | AF58: 1.59 | AG58: 2.07 | AH58: =Z58*0.1-Z58 -> -1.971 | AI58: =AF58*0.4+AF58 -> 2.226 | AJ58: =1-AF58/Z58 -> 0.2739726
B59: simple | C59: 900782 | D59: Brochas de pintar 3pc / paint brushes 3 pc - 900782 | E59: 1 | F59: 0 | G59: visible | H59: Polyester Paint Brush Set | I59: Arora offers a complete range of color-coded brush wallets. With the Arora Synthetic Brush Set, all an artist needs is paint to begin the journey towards broadening their creative and artistic horizons. Arora brings to you this Flat Paint Brush set so that you can effortlessly create thick lines. This Arora set consists of 3 brushes which can be used by artists and also by amateurs. Ideal for for acrylic, watercolor and gauche paints. Set Contents: 3 Flat White Synthetic Hair Brush with plastic handle | N59: 1 | O59: 1000 | Z59: 0.99 | AA59: Tools | AB59: https://fantasydiscountwholesale.com/wp-content/uploads/2023/10/900782-1.jpeg | AC59: 2-5 | AD59: 12 | AE59: =AD59 -> 12 | AF59: 0.67 | AG59: =AF59*0.4+AF59 -> 0.938 | AH59: =Z59*0.1-Z59 -> -0.891 | AI59: =AF59*0.4+AF59 -> 0.938 | AJ59: =1-AF59/Z59 -> 0.32323232
B60: simple | C60: FD2206 | D60: pequena cinta 6pc / 6pc small tape - FD2206 | E60: 1 | F60: 0 | G60: visible | H60: pequena cinta 6pc / 6pc small tape - FD2206 | I60: Water Repellant Paper Tape That Is Ideal For All Painting Jobs Yields Sharp Edges In All Kinds Of Painter Jobs At Home, Offices, Industries, And More Clean Removal Without Leaving Residue Easy To Tear Paper Tape For Everyday Use | N60: 1 | O60: 1000 | Z60: 1.25 | AA60: School | AB60: https://fantasydiscountwholesale.com/wp-content/uploads/2023/10/2206.jpeg | AC60: 2-5 | AD60: 6 | AE60: =AD60 -> 6 | AF60: 0.72 | AG60: =AF60*0.6+AF60 -> 1.152 | AH60: =Z60*0.1-Z60 -> -1.125 | AI60: =AF60*0.4+AF60 -> 1.008 | AJ60: =1-AF60/Z60 -> 0.424
B61: simple | C61: 600290 | D61: Notebook - 600290 | E61: 1 | F61: 0 | G61: visible | H61: Small notebook with pen | I61: Introducing our Small Notebook with Pen, the perfect companion for jotting down notes on the go. Compact and lightweight, it fits easily into your pocket or bag, ensuring you're always prepared to capture your ideas and thoughts. Complete with a convenient pen holder, so you'll never be without a writing tool. Ideal for students, professionals, and anyone who loves to stay organized. | N61: 1 | O61: 1000 | Z61: 1.19 | AA61: School | AB61: https://fantasydiscountwholesale.com/wp-content/uploads/2024/03/600290.jpeg | AC61: 2-5 | AD61: 6 | AE61: =AD61 -> 6 | AF61: 0.75 | AG61: =AF61*0.45+AF61 -> 1.0875 | AH61: =Z61*0.1-Z61 -> -1.071 | AI61: =AF61*0.4+AF61 -> 1.05 | AJ61: =1-AF61/Z61 -> 0.3697479
B62: simple | C62: 600289 | D62: Notebook - 600289 | E62: 1 | F62: 0 | G62: visible | H62: 32" notebook with pen | I62: The 32" Notebook with Pen offers ample space for all your writing and sketching needs. With its large size, it provides plenty of room for creativity and productivity. Complete with a convenient pen holder, ensuring your writing instrument is always within reach. Ideal for artists, designers, and anyone who appreciates a spacious workspace. | N62: 1 | O62: 1000 | Z62: 1.99 | AA62: School | AB62: https://fantasydiscountwholesale.com/wp-content/uploads/2024/03/600289.jpeg | AC62: 2-5 | AD62: 6 | AE62: =AD62 -> 6 | AF62: 1.26 | AG62: =AF62*0.5+AF62 -> 1.89 | AH62: =Z62*0.1-Z62 -> -1.791 | AI62: =AF62*0.4+AF62 -> 1.764 | AJ62: =1-AF62/Z62 -> 0.36683417
B63: simple | C63: 503743 | D63: Soap case smile face - 503743 | E63: 0 | F63: 0 | G63: hidden | H63: Soap case smile face - 503743 | I63: Soap Case Smile Face (503743) features a fun and cheerful design, perfect for keeping soap dry and mess-free. Its compact and durable design makes it ideal for bathrooms, kitchens, or travel. Great for retail, home essentials, and wholesale stores. | N63: 0 | O63: 0 | Z63: 0.79 | AA63: Bathroom | AB63: https://fantasydiscountwholesale.com/wp-content/uploads/2025/04/503743.jpg | AC63: 2-5 | AD63: 12 | AE63: =AD63 -> 12 | AF63: 0.52 | AG63: =AF63*0.42+AF63 -> 0.7384 | AH63: =Z63*0.1-Z63 -> -0.711 | AI63: =AF63*0.4+AF63 -> 0.728 | AJ63: =1-AF63/Z63 -> 0.34177215
B64: simple | C64: 505797 | D64: Soap holder transparent - 505797 | E64: 1 | F64: 0 | G64: visible | H64: Soap holder transparent - 505797 | I64: Soap Holder Transparent (505797) features a sleek and minimalistic design, keeping soap dry and extending its lifespan. Perfect for bathrooms, kitchens, or travel. Ideal for retail, home essentials, and wholesale stores. | N64: 1 | O64: 1000 | Z64: 0.89 | AA64: Bathroom | AB64: https://fantasydiscountwholesale.com/wp-content/uploads/2025/04/505797.jpg | AC64: 2-5 | AD64: 12 | AE64: =AD64 -> 12 | AF64: 0.57 | AG64: =AF64*0.4+AF64 -> 0.798 | AH64: =Z64*0.1-Z64 -> -0.801 | AI64: =AF64*0.4+AF64 -> 0.798 | AJ64: =1-AF64/Z64 -> 0.35955056
B65: simple | C65: 2026 | D65: Melamine plate 9" 107g - 2026 | E65: 1 | F65: 0 | G65: visible | H65: Melamine plate 9" 107g | I65: Enhance your tableware collection with our 9" Melamine Plates with different designs. These plates are perfect for everyday use. The 9-inch size is ideal for serving a variety of dishes, from main courses to generous salads. A great choice for restaurants, catering services, or home use. | N65: 1 | O65: 1000 | Z65: 0.85 | AA65: Kitchen | AB65: https://fantasydiscountwholesale.com/wp-content/uploads/2023/10/2026-1.jpeg | AC65: 2-6 | AD65: 12 | AE65: =AD65 -> 12 | AF65: 0.31 | AG65: =AF65*1.25+AF65 -> 0.6975 | AH65: =Z65*0.1-Z65 -> -0.765 | AI65: =AF65*0.4+AF65 -> 0.434 | AJ65: =1-AF65/Z65 -> 0.63529412
B66: simple | C66: 5728 | D66: Melamine Bowl 8" (110 g) soup - 5728 | E66: 1 | F66: 0 | G66: visible | H66: Soup Melamine Bowl 8" (110 g) | I66: Enhance your tableware collection with our 8" Soup Melamine Bowl with different designs. These Bowls are perfect for everyday use. The 8-inch size is ideal for serving soups. A great choice for restaurants, catering services, or home use. | N66: 1 | O66: 1000 | Z66: 0.85 | AA66: Kitchen | AB66: https://fantasydiscountwholesale.com/wp-content/uploads/2023/10/CK-5728-1.jpeg | AC66: 2-6 | AD66: 12 | AE66: =AD66 -> 12 | AF66: 0.28 | AG66: =AF66*1.5+AF66 -> 0.7 | AH66: =Z66*0.1-Z66 -> -0.765 | AI66: =AF66*0.4+AF66 -> 0.392 | AJ66: =1-AF66/Z66 -> 0.67058824
B67: simple | C67: 5749 | D67: Melamine Bowl 9" soup - 5749 | E67: 1 | F67: 0 | G67: visible | H67: Soup Melamine Bowl 9" | I67: Enhance your tableware collection with our 9" Soup Melamine Bowl with different designs. These Bowls are perfect for everyday use. The 9-inch size is ideal for serving soups. A great choice for restaurants, catering services, or home use. | N67: 1 | O67: 1000 | Z67: 0.85 | AA67: Kitchen | AB67: https://fantasydiscountwholesale.com/wp-content/uploads/2023/10/5749.jpeg | AC67: 2-6 | AD67: 12 | AE67: =AD67 -> 12 | AF67: 0.3 | AG67: =AF67*1.32+AF67 -> 0.696 | AH67: =Z67*0.1-Z67 -> -0.765 | AI67: =AF67*0.4+AF67 -> 0.42 | AJ67: =1-AF67/Z67 -> 0.64705882
B68: simple | C68: 3296-9 | D68: Melamine Bowl 9" (110 g) soup - 3296-9 | E68: 1 | F68: 0 | G68: visible | H68: Soup Melamine Bowl 9" (110 g) | I68: Enhance your tableware collection with our 9" Soup Melamine Bowl with different designs. These Bowls are perfect for everyday use. The 9-inch size is ideal for serving soups. A great choice for restaurants, catering services, or home use. | N68: 1 | O68: 1000 | Z68: 0.85 | AA68: Kitchen | AB68: https://fantasydiscountwholesale.com/wp-content/uploads/2023/10/3296-9-1.jpeg | AC68: 2-6 | AD68: 12 | AE68: =AD68 -> 12 | AF68: 0.35 | AG68: =AF68*1+AF68 -> 0.7 | AH68: =Z68*0.1-Z68 -> -0.765 | AI68: =AF68*0.4+AF68 -> 0.49 | AJ68: =1-AF68/Z68 -> 0.58823529
B69: simple | C69: 3294-9 | D69: Melamine Bowl 9" (110 g) soup - 3294-9 | E69: 1 | F69: 0 | G69: visible | H69: Soup Melamine Bowl 9" (110 g) | I69: Enhance your tableware collection with our 9" Soup Melamine Bowl with different designs. These Bowls are perfect for everyday use. The 9-inch size is ideal for serving soups. A great choice for restaurants, catering services, or home use. | N69: 1 | O69: 1000 | Z69: 0.85 | AA69: Kitchen | AB69: https://fantasydiscountwholesale.com/wp-content/uploads/2023/10/94-9-1.jpeg | AC69: 2-6 | AD69: 12 | AE69: =AD69 -> 12 | AF69: 0.36 | AG69: =AF69*0.94+AF69 -> 0.6984 | AH69: =Z69*0.1-Z69 -> -0.765 | AI69: =AF69*0.4+AF69 -> 0.504 | AJ69: =1-AF69/Z69 -> 0.57647059
B70: simple | C70: P3849 | D70: Melamine plate 9" 103g - P3849 | E70: 0 | F70: 0 | G70: hidden | H70: Melamine plate 9" 103g | I70: Enhance your tableware collection with our 9" Melamine Plates with different designs. These plates are perfect for everyday use. The 9-inch size is ideal for serving a variety of dishes, from main courses to generous salads. A great choice for restaurants, catering services, or home use. | N70: 0 | O70: 0 | Z70: 0.85 | AA70: Kitchen | AB70: https://fantasydiscountwholesale.com/wp-content/uploads/2023/10/3849.jpeg | AC70: 2-6 | AD70: 12 | AE70: =AD70 -> 12 | AF70: 0.31 | AG70: =AF70*1.25+AF70 -> 0.6975 | AH70: =Z70*0.1-Z70 -> -0.765 | AI70: =AF70*0.4+AF70 -> 0.434 | AJ70: =1-AF70/Z70 -> 0.63529412
B71: simple | C71: 6779 | D71: Glass Marbles - 6773 | E71: 1 | F71: 0 | G71: visible | H71: Glass Marbles - 6773 | I71: Enhance your collection with our exquisite Marbles! These beautifully crafted glass spheres come in a variety of vibrant colors and patterns. Perfect for games, crafting, or simply as unique décor pieces. Add a touch of elegance to your surroundings. Order yours today! | N71: 1 | O71: 1000 | Z71: 0.8 | AA71: Toys | AB71: https://fantasydiscountwholesale.com/wp-content/uploads/2023/10/FD-2209-1.jpeg | AC71: 2-7 | AD71: 12 | AE71: =AD71 -> 12 | AF71: 0.54 | AG71: =AF71*1.87+AF71 -> 1.5498 | AH71: =Z71*0.1-Z71 -> -0.72 | AI71: =AF71*0.4+AF71 -> 0.756 | AJ71: =1-AF71/Z71 -> 0.325
B72: simple | C72: 82165 | D72: Candle / oil & wax burner set lavender - 82165 | E72: 0 | F72: 0 | G72: hidden | H72: Candle / oil & wax burner set lavender - 82165 | I72: Candle/Oil & Wax Burner Set Lavender (82165) creates a calming ambiance with a soothing lavender scent. Perfect for aromatherapy, relaxation, and home décor. Ideal for use with essential oils or wax melts. Great for wholesale and discount stores. | N72: 0 | O72: 0 | Z72: 4.59 | AA72: Air Freshener | AB72: https://fantasydiscountwholesale.com/wp-content/uploads/2025/02/82165.jpeg | AC72: 2-7 | AD72: 2 | AE72: =AD72 -> 2 | AF72: 3.06 | AG72: =AF72*0.402+AF72 -> 4.29012 | AH72: =Z72*0.1-Z72 -> -4.131 | AI72: =AF72*0.4+AF72 -> 4.284 | AJ72: =1-AF72/Z72 -> 0.33333333
B73: simple | C73: 82167 | D73: Candle / oil & wax burner set vanilla - 82167 | E73: 1 | F73: 0 | G73: visible | H73: Candle / oil & wax burner set vanilla - 82167 | I73: Candle/Oil & Wax Burner Set Vanilla (82167) fills any space with a warm and comforting vanilla scent. Perfect for aromatherapy, relaxation, and home décor. Designed for use with essential oils or wax melts. Ideal for wholesale and discount stores. | N73: 1 | O73: 1000 | Z73: 4.59 | AA73: Air Freshener | AB73: https://fantasydiscountwholesale.com/wp-content/uploads/2025/02/82167.jpeg | AC73: 2-7 | AD73: 2 | AE73: =AD73 -> 2 | AF73: 3.06 | AG73: =AF73*0.402+AF73 -> 4.29012 | AH73: =Z73*0.1-Z73 -> -4.131 | AI73: =AF73*0.4+AF73 -> 4.284 | AJ73: =1-AF73/Z73 -> 0.33333333
B74: simple | C74: 82166 | D74: Candle / oil & wax burner set fresh linen - 82166 | E74: 1 | F74: 0 | G74: visible | H74: Candle / oil & wax burner set fresh linen - 82166 | I74: Candle/Oil & Wax Burner Set Fresh Linen (82166) infuses your space with the crisp, clean scent of fresh laundry. Perfect for aromatherapy, relaxation, and home décor. Designed for use with essential oils or wax melts. Ideal for wholesale and discount stores. | N74: 1 | O74: 1000 | Z74: 4.59 | AA74: Air Freshener | AB74: https://fantasydiscountwholesale.com/wp-content/uploads/2025/02/82166.jpeg | AC74: 2-7 | AD74: 2 | AE74: =AD74 -> 2 | AF74: 3.06 | AG74: =AF74*0.402+AF74 -> 4.29012 | AH74: =Z74*0.1-Z74 -> -4.131 | AI74: =AF74*0.4+AF74 -> 4.284 | AJ74: =1-AF74/Z74 -> 0.33333333
B75: simple | C75: 82164 | D75: Candle / oil & wax burner set apple cinamon - 82164 | E75: 1 | F75: 0 | G75: visible | H75: Candle / oil & wax burner set apple cinamon - 82164 | I75: Candle/Oil & Wax Burner Set Apple Cinnamon (82164) fills your space with the warm, inviting scent of crisp apples and spicy cinnamon. Perfect for aromatherapy, relaxation, and home décor. Designed for use with essential oils or wax melts. Ideal for wholesale and discount stores. | N75: 1 | O75: 1000 | Z75: 4.59 | AA75: Air Freshener | AB75: https://fantasydiscountwholesale.com/wp-content/uploads/2025/02/82164.jpeg | AC75: 2-7 | AD75: 2 | AE75: =AD75 -> 2 | AF75: 3.06 | AG75: =AF75*0.402+AF75 -> 4.29012 | AH75: =Z75*0.1-Z75 -> -4.131 | AI75: =AF75*0.4+AF75 -> 4.284 | AJ75: =1-AF75/Z75 -> 0.33333333
B76: simple | C76: 8821 | D76: River rock - 8821 | E76: 1 | F76: 0 | G76: visible | H76: River rock - 8821 | I76: River Rock (8821) features smooth, natural stones perfect for home décor, landscaping, aquariums, or craft projects. Adds a stylish and organic touch to any setting. Ideal for retail, gardening, and wholesale stores. | N76: 1 | O76: 1000 | Z76: 0.8 | AA76: Miscellaneous | AB76: https://fantasydiscountwholesale.com/wp-content/uploads/2023/10/6033-piedras-de-rio.jpeg | AC76: 2-7 | AD76: 12 | AE76: =AD76 -> 12 | AF76: 0.54 | AG76: =AF76*0.46+AF76 -> 0.7884 | AH76: =Z76*0.1-Z76 -> -0.72 | AI76: =AF76*0.4+AF76 -> 0.756 | AJ76: =1-AF76/Z76 -> 0.325
B77: simple | C77: 98112 | D77: Ice tray set 2 pc - 98112 | E77: 1 | F77: 0 | G77: visible | H77: 2 Pcs Ice tray set | I77: Each tray in the set can produce a substantial number of ice cubes, making them perfect for preparing ice for daily use. This Ice Tray Set is a practical and essential addition to any household. | N77: 1 | O77: 1000 | Z77: 1 | AA77: Kitchen | AB77: https://fantasydiscountwholesale.com/wp-content/uploads/2023/10/81-12-hielera.jpeg | AC77: 3-2 | AD77: 12 | AE77: =AD77 -> 12 | AF77: 0.46 | AG77: =AF77*0.84+AF77 -> 0.8464 | AH77: =Z77*0.1-Z77 -> -0.9 | AI77: =AF77*0.4+AF77 -> 0.644 | AJ77: =1-AF77/Z77 -> 0.54
B78: simple | C78: FD812 | D78: Kitchen Sink Strainer - FD812 | E78: 0 | F78: 0 | G78: hidden | H78: Kitchen Sink Strainer | I78: Offer your customers the ultimate solution in kitchen convenience with our Sink Screens Strainer. This strainers effectively prevent food particles and debris from clogging drains while allowing water to flow freely. Stock up on this indispensable set for a hassle-free, efficient kitchen experience. | N78: 0 | O78: 0 | Z78: 0.65 | AA78: Kitchen | AB78: https://fantasydiscountwholesale.com/wp-content/uploads/2023/10/FD812-1.jpeg | AC78: 3-2 | AD78: 12 | AE78: =AD78 -> 12 | AF78: 0.26 | AG78: =AF78*1.1+AF78 -> 0.546 | AH78: =Z78*0.1-Z78 -> -0.585 | AI78: =AF78*0.4+AF78 -> 0.364 | AJ78: =1-AF78/Z78 -> 0.6
B79: simple | C79: 803100 | D79: 1 Rat trap - 803100 | E79: 1 | F79: 0 | G79: visible | H79: 1 Rat trap - 803100 | I79: Put an end to unwanted guests with our Rat Trap. This highly effective solution is designed to catch and secure rodents quickly and safely. Easy to set up and reusable, our rat trap is a reliable choice for pest control. Say goodbye to rodent problems – safeguard your space with our Rat Trap. Get yours today for peace of mind. | N79: 1 | O79: 1000 | Z79: 0.65 | AA79: Tools | AB79: https://fantasydiscountwholesale.com/wp-content/uploads/2023/10/803100-1.jpeg | AC79: 3-2 | AD79: 12 | AE79: =AD79 -> 12 | AF79: 0.4 | AG79: =AF79*0.47+AF79 -> 0.588 | AH79: =Z79*0.1-Z79 -> -0.585 | AI79: =AF79*0.4+AF79 -> 0.56 | AJ79: =1-AF79/Z79 -> 0.38461538
B80: simple | C80: FD470 | D80: Hamper foldable popups (colored) 40*70 - FD470 | E80: 1 | F80: 0 | G80: visible | H80: Hamper foldable popups (colored) 40*70 - FD470 | I80: Simplify your laundry routine with our Popup Hamper Collection. These space-saving and collapsible hampers are designed for convenience and style. Featuring durable materials and a variety of sizes and designs, our hampers make laundry day a breeze. Keep your space tidy and organized effortlessly – order your Popup Hamper today! | N80: 1 | O80: 1000 | Z80: 1.09 | AA80: Miscellaneous | AB80: https://fantasydiscountwholesale.com/wp-content/uploads/2023/10/4070.jpeg | AC80: 3-2 | AD80: 6 | AE80: =AD80 -> 6 | AF80: 0.72 | AG80: =AF80*0.39+AF80 -> 1.0008 | AH80: =Z80*0.1-Z80 -> -0.981 | AI80: =AF80*0.4+AF80 -> 1.008 | AJ80: =1-AF80/Z80 -> 0.33944954
B81: simple | C81: FD697 | D81: 3pc box cutter - FD697 | E81: 1 | F81: 0 | G81: visible | H81: 3pc box cutter - FD697 | I81: Multipurpose Utility Knife set with a segmented blade that slides out and locks. These box cutter knives are a must have item in every home. Never get stuck not being able to open a box again. The LOCK keeps the blade tightly clamped when in use. As the cutting edge becomes dull, it can be broken off and the remaining sharp blade segments are ready for use. | N81: 1 | O81: 1000 | Z81: 0.75 | AA81: Tools | AB81: https://fantasydiscountwholesale.com/wp-content/uploads/2023/10/FD697.jpeg | AC81: 3-2 | AD81: 12 | AE81: =AD81 -> 12 | AF81: 0.32 | AG81: =AF81*0.86+AF81 -> 0.5952 | AH81: =Z81*0.1-Z81 -> -0.675 | AI81: =AF81*0.4+AF81 -> 0.448 | AJ81: =1-AF81/Z81 -> 0.57333333
B82: simple | C82: FD221057 | D82: Candado 2pc / lock 2pc - FD221057 | E82: 1 | F82: 0 | G82: visible | H82: Candado 2pc / lock 2pc - FD221057 | I82: Made of 4-pin brass to withstand tamper and weather resistance and give you smooth operation. The long shackle is hardened steel to withstand long use and cut resistance. The closures have a layer of steel joined by 8 solid steel stakes to provide maximum security. It is ideal for home, office, commercial, construction, gates and fences in high security environments. | N82: 1 | O82: 1000 | Z82: 0.95 | AA82: Tools | AB82: https://fantasydiscountwholesale.com/wp-content/uploads/2023/10/221057-1.jpeg | AC82: 3-2 | AD82: 12 | AE82: =AD82 -> 12 | AF82: 0.44 | AG82: =AF82*0.79+AF82 -> 0.7876 | AH82: =Z82*0.1-Z82 -> -0.855 | AI82: =AF82*0.4+AF82 -> 0.616 | AJ82: =1-AF82/Z82 -> 0.53684211
B83: simple | C83: 3317 | D83: Multifunctional Brush - 3317 | E83: 1 | F83: 0 | G83: visible | H83: Multifunctional Cleaning scrub brush with plastic handle | I83: Experience the power of versatility with our Multifunctional Cleaning Scrub Brush featuring a sturdy plastic handle. This essential cleaning tool is designed to tackle a wide range of cleaning tasks with ease. From scrubbing stubborn stains in your kitchen to tackling grime in the bathroom, its durable bristles get the job done effectively. The ergonomic plastic handle provides a comfortable grip for extended use. Elevate your cleaning routine and achieve spotless results in no time with our Multifunctional Cleaning Scrub Brush. Make your cleaning tasks effortless and efficient - order yours today! 🧼🪣🧽 | N83: 1 | O83: 1000 | Z83: 0.65 | AA83: cleaning supplies | AB83: https://fantasydiscountwholesale.com/wp-content/uploads/2023/10/3317-cepillo.jpeg | AC83: 3-3 | AD83: 12 | AE83: =AD83 -> 12 | AF83: 0.34 | AG83: =AF83*0.62+AF83 -> 0.5508 | AH83: =Z83*0.1-Z83 -> -0.585 | AI83: =AF83*0.4+AF83 -> 0.476 | AJ83: =1-AF83/Z83 -> 0.47692308
B84: simple | C84: XR2025 | D84: Stainless Steel S shaped 3 hooks - XR2025 | E84: 1 | F84: 0 | G84: visible | H84: Stainless Steel S shaped 3 hooks | I84: stainless steel. Rubber tip cover on 2 ends of the hook. Great for hanging apparel kitchenware utelsils, plants, towels, pots ,Office and Home organize. Add-a-hook' on closet/shower curtain rods, doors; hang plants almost anywhere | N84: 1 | O84: 1000 | Z84: 0.85 | AA84: Kitchen | AB84: https://fantasydiscountwholesale.com/wp-content/uploads/2023/10/XR2025.jpeg | AC84: 3-3 | AD84: 12 | AE84: =AD84 -> 12 | AF84: 0.38 | AG84: =AF84*0.83+AF84 -> 0.6954 | AH84: =Z84*0.1-Z84 -> -0.765 | AI84: =AF84*0.4+AF84 -> 0.532 | AJ84: =1-AF84/Z84 -> 0.55294118
B85: simple | C85: TT1811-48 | D85: Plastic clothes pins (colored 48 pcs) - TT1811-48 | E85: 0 | F85: 0 | G85: hidden | H85: Plastic clothes pins (colored 48 pcs) | I85: nhance your laundry essentials with our colorful 48-piece Plastic Clothes Pins set in green, yellow, red, and blue. Ideal for wholesale, these sturdy, weather-resistant pins offer a strong hold for all fabrics. Their bright colors add a fun, cheerful touch to everyday laundry tasks, ensuring reliability and style | N85: 0 | O85: 0 | Z85: 1.99 | AA85: cleaning supplies | AB85: https://fantasydiscountwholesale.com/wp-content/uploads/2023/10/11-48.jpeg | AC85: 3-3 | AD85: 6 | AE85: =AD85 -> 6 | AF85: 0.88 | AG85: =AF85*0.88+AF85 -> 1.6544 | AH85: =Z85*0.1-Z85 -> -1.791 | AI85: =AF85*0.4+AF85 -> 1.232 | AJ85: =1-AF85/Z85 -> 0.55778894
B86: simple | C86: FD524 | D86: Knife Cutter - FD524 | E86: 1 | F86: 0 | G86: visible | H86: high-quality multi-purpose snap blade knife with a keen cutting edge for arts, crafts and utility | I86: Cutter Knife: A versatile and essential tool for precision cutting tasks. Ideal for a variety of applications, from crafting to opening packages. | N86: 1 | O86: 1000 | Z86: 0.75 | AA86: Tools | AB86: https://fantasydiscountwholesale.com/wp-content/uploads/2023/10/FD524-1.jpeg | AC86: 3-3 | AD86: 12 | AE86: =AD86 -> 12 | AF86: 0.3 | AG86: =AF86*1.16+AF86 -> 0.648 | AH86: =Z86*0.1-Z86 -> -0.675 | AI86: =AF86*0.4+AF86 -> 0.42 | AJ86: =1-AF86/Z86 -> 0.6
B87: simple | C87: CH91033 | D87: Lemon Squeezer - CH91033 | E87: 1 | F87: 0 | G87: visible | H87: Lemon Squeezer - CH91033 | I87: Offer your customers the convenience of fresh juice with our Single Press Manual Lemon Squeezer. Efficient and easy to use, this sturdy juicer extracts maximum juice with minimal effort. Ideal for kitchens and bars, its compact design and durable construction make it a must-have for citrus lovers. | N87: 1 | O87: 1000 | Z87: 3.05 | AA87: Kitchen | AB87: https://fantasydiscountwholesale.com/wp-content/uploads/2026/02/CH91033.jpeg | AC87: 3-3 | AD87: 6 | AE87: =AD87 -> 6 | AF87: 2.03 | AG87: =AF87*0.4+AF87 -> 2.842 | AH87: =Z87*0.1-Z87 -> -2.745 | AI87: =AF87*0.4+AF87 -> 2.842 | AJ87: =1-AF87/Z87 -> 0.33442623
B88: simple | C88: 003-680 | D88: Soporte para telefono / Phone holder -003-680 | E88: 1 | F88: 0 | G88: visible | H88: Cell Phone Stand, Lamicall Phone Holder | I88: The weighted base and aluminum rod bring extreme stability, sturdiness and durability. Matched with rubber feet under the base, whether picking and placing device or tapping your cell phone, the stand will remain stable and will not slide. | N88: 1 | O88: 1000 | Z88: 4.5 | AA88: Miscellaneous | AB88: https://fantasydiscountwholesale.com/wp-content/uploads/2023/10/003-680.jpeg | AC88: 3-3 | AD88: 3 | AE88: =AD88 -> 3 | AF88: 2.75 | AG88: =AF88*0.453+AF88 -> 3.99575 | AH88: =Z88*0.1-Z88 -> -4.05 | AI88: =AF88*0.4+AF88 -> 3.85 | AJ88: =1-AF88/Z88 -> 0.38888889
B89: simple | C89: CH86439 | D89: Anntena With Base - CH86439 | E89: 1 | F89: 0 | G89: visible | H89: Anntena With Base - CH86439 | I89: Antenna with Base – CH86439: Compact indoor antenna with sturdy base for stable reception. Easy to install and compatible with various devices. Ideal for wholesale to electronics and home goods retailers. | N89: 1 | O89: 1000 | Z89: 1.49 | AA89: Tools | AB89: https://fantasydiscountwholesale.com/wp-content/uploads/2025/06/CH86439.jpg | AC89: 3-3 | AD89: 6 | AE89: =AD89 -> 6 | AF89: 1 | AG89: =AF89*0.4+AF89 -> 1.4 | AH89: =Z89*0.1-Z89 -> -1.341 | AI89: =AF89*0.4+AF89 -> 1.4 | AJ89: =1-AF89/Z89 -> 0.32885906
B90: simple | C90: 40844 | D90: Dove spray Apple&white tea 150 ML / 5.07 OZ - 40844 | E90: 0 | F90: 0 | G90: hidden | H90: Dove spray Apple&white tea 150 ML / 5.07 OZ | I90: Comprehensive and well organized. A much more practical and cost-effective way to purchase hardware than individually. You would have no worry to spend a lot of time in finding the correct screws, as INDPROD customized assortment would meet all your demands. Everything is labeled on the case for easily finding the size you need. | N90: 0 | O90: 0 | Z90: 2.85 | AA90: Beauty & Personal Care | AB90: https://fantasydiscountwholesale.com/wp-content/uploads/2024/02/40844.jpeg | AC90: 3-4 | AD90: 6 | AE90: =AD90 -> 6 | AF90: 2.08 | AG90: =AF90*0.37+AF90 -> 2.8496 | AH90: =Z90*0.1-Z90 -> -2.565 | AI90: =AF90*0.4+AF90 -> 2.912 | AJ90: =1-AF90/Z90 -> 0.27017544
B91: simple | C91: 71552 | D91: Dove spray Beauty finish 150 ML / 5.07 OZ - 71552 | E91: 0 | F91: 0 | G91: hidden | H91: Spray on all-day freshness with this Dove antiperspirant for a cool cucumber and green tea scent, superb underarm care | I91: 48-Hour antiperspirant protection comes with a super fresh scent, when you spray on dove go fresh pomegranate & lemon verbena antiperspirant deodorant spray. Feel refreshed every day with 48 hours of antiperspirant protection and superb underarm care, from dove go fresh. | N91: 0 | O91: 0 | Z91: 2.85 | AA91: Beauty & Personal Care | AB91: https://fantasydiscountwholesale.com/wp-content/uploads/2024/02/71552.jpeg | AC91: 3-4 | AD91: 6 | AE91: =AD91 -> 6 | AF91: 2.08 | AG91: =AF91*0.37+AF91 -> 2.8496 | AH91: =Z91*0.1-Z91 -> -2.565 | AI91: =AF91*0.4+AF91 -> 2.912 | AJ91: =1-AF91/Z91 -> 0.27017544
B92: simple | C92: 40855 | D92: Dove spray Coconut 150 ML / 5.07 OZ - 40855 | E92: 1 | F92: 0 | G92: visible | H92: Spray on all-day freshness with this Dove antiperspirant for a cool cucumber and green tea scent, superb underarm care | I92: 48-Hour antiperspirant protection comes with a super fresh scent, when you spray on dove go fresh pomegranate & lemon verbena antiperspirant deodorant spray. Feel refreshed every day with 48 hours of antiperspirant protection and superb underarm care, from dove go fresh. | N92: 1 | O92: 1000 | Z92: 2.85 | AA92: Beauty & Personal Care | AB92: https://fantasydiscountwholesale.com/wp-content/uploads/2023/11/40855.jpeg | AC92: 3-4 | AD92: 6 | AE92: =AD92 -> 6 | AF92: 2.1 | AG92: =AF92*0.37+AF92 -> 2.877 | AH92: =Z92*0.1-Z92 -> -2.565 | AI92: =AF92*0.4+AF92 -> 2.94 | AJ92: =1-AF92/Z92 -> 0.26315789
B93: simple | C93: 71553 | D93: Dove spray Cucumber 150 ML / 5.07 OZ - 71553 | E93: 1 | F93: 0 | G93: visible | H93: Dove spray Cucumber 150 ML / 5.07 OZ - 71553 | I93: Dove Spray Cucumber 150ml / 5.07oz – 71553 offers 48-hour freshness with a crisp cucumber scent. Gentle on skin with moisturizing ingredients. Ideal for wholesale to beauty stores, pharmacies, and retailers. | N93: 1 | O93: 1000 | Z93: 2.85 | AA93: Beauty & Personal Care | AB93: https://fantasydiscountwholesale.com/wp-content/uploads/2023/10/71553-1.jpeg | AC93: 3-4 | AD93: 6 | AE93: =AD93 -> 6 | AF93: 2.05 | AG93: =AF93*0.39+AF93 -> 2.8495 | AH93: =Z93*0.1-Z93 -> -2.565 | AI93: =AF93*0.4+AF93 -> 2.87 | AJ93: =1-AF93/Z93 -> 0.28070175
B94: simple | C94: 55132 | D94: Dove spray 150 ML Men sport - 55132 | E94: 0 | F94: 0 | G94: hidden | H94: Dove spray 150 ML Men sport active & fresh | I94: Revitalize your product lineup with Dove Spray 150ml for Men Sport Active & Fresh. This wholesale gem offers a burst of freshness and lasting fragrance. Elevate your inventory with the invigorating scent of active masculinity. | N94: 0 | O94: 0 | Z94: 2.85 | AA94: Beauty & Personal Care | AB94: https://fantasydiscountwholesale.com/wp-content/uploads/2023/12/55132.jpeg | AC94: 3-4 | AD94: 6 | AE94: =AD94 -> 6 | AF94: 2.08 | AG94: =AF94*0.37+AF94 -> 2.8496 | AH94: =Z94*0.1-Z94 -> -2.565 | AI94: =AF94*0.4+AF94 -> 2.912 | AJ94: =1-AF94/Z94 -> 0.27017544
B95: simple | C95: 99740 | D95: Dove spray 150 ML invisible dry Men - 99740 | E95: 0 | F95: 0 | G95: hidden | H95: Dove spray 150 ML Men invisible dry | I95: Introducing Dove Spray 150ml for Men Invisible Dry. A wholesale must-have, providing long-lasting protection without residue. Elevate your inventory with this invisible and effective solution for confident freshness | N95: 0 | O95: 0 | Z95: 2.85 | AA95: Beauty & Personal Care | AB95: https://fantasydiscountwholesale.com/wp-content/uploads/2023/12/99740.jpeg | AC95: 3-4 | AD95: 6 | AE95: =AD95 -> 6 | AF95: 1.92 | AG95: =AF95*0.482+AF95 -> 2.84544 | AH95: =Z95*0.1-Z95 -> -2.565 | AI95: =AF95*0.4+AF95 -> 2.688 | AJ95: =1-AF95/Z95 -> 0.32631579
B96: simple | C96: 99738 | D96: Dove spray Invisible dry 150 ML / 5.07 OZ - 99738 | E96: 1 | F96: 0 | G96: visible | H96: Dove invisible Dry 48-Hour Anti-Perspirant Spray 4oz | I96: Dove invisible dry anti-perspirant gives you serious protection from body odor & sweaty pits, without the deodorant stains. it’s invincible and invisible! provides 48-hour protection. invisibility that holds up - tested on 100 colors with 1/4 moisturizing cream to nourish skin. 0% alcohol, anti-perspirant spray | N96: 1 | O96: 1000 | Z96: 2.85 | AA96: Beauty & Personal Care | AB96: https://fantasydiscountwholesale.com/wp-content/uploads/2023/10/99738.jpeg | AC96: 3-4 | AD96: 6 | AE96: =AD96 -> 6 | AF96: 2.08 | AG96: =AF96*0.37+AF96 -> 2.8496 | AH96: =Z96*0.1-Z96 -> -2.565 | AI96: =AF96*0.4+AF96 -> 2.912 | AJ96: =1-AF96/Z96 -> 0.27017544
B97: simple | C97: 71497 | D97: Dove spray Original 150 ML / 5.07 OZ - 71497 | E97: 1 | F97: 0 | G97: visible | H97: Dove ORIGINAL Anti-Perspirant Spray 4oz | I97: Dove invisible dry anti-perspirant gives you serious protection from body odor & sweaty pits, without the deodorant stains. it’s invincible and invisible! provides 48-hour protection. invisibility that holds up - tested on 100 colors with 1/4 moisturizing cream to nourish skin. 0% alcohol, anti-perspirant spray | N97: 1 | O97: 1000 | Z97: 2.85 | AA97: Beauty & Personal Care | AB97: https://fantasydiscountwholesale.com/wp-content/uploads/2023/10/71497-1.jpeg | AC97: 3-4 | AD97: 6 | AE97: =AD97 -> 6 | AF97: 2.05 | AG97: =AF97*0.39+AF97 -> 2.8495 | AH97: =Z97*0.1-Z97 -> -2.565 | AI97: =AF97*0.4+AF97 -> 2.87 | AJ97: =1-AF97/Z97 -> 0.28070175
B98: simple | C98: 000131 | D98: Dove spray Pomegranade 150 ML / 5.07 OZ - 000131 | E98: 1 | F98: 0 | G98: visible | H98: Dove POMEGRANADE Anti-Perspirant Spray 4oz | I98: Dove invisible dry anti-perspirant gives you serious protection from body odor & sweaty pits, without the deodorant stains. it’s invincible and invisible! provides 48-hour protection. invisibility that holds up - tested on 100 colors with 1/4 moisturizing cream to nourish skin. 0% alcohol, anti-perspirant spray | N98: 1 | O98: 1000 | Z98: 2.85 | AA98: Beauty & Personal Care | AB98: https://fantasydiscountwholesale.com/wp-content/uploads/2024/02/40843-1.jpeg | AC98: 3-4 | AD98: 6 | AE98: =AD98 -> 6 | AF98: 2.08 | AG98: =AF98*0.37+AF98 -> 2.8496 | AH98: =Z98*0.1-Z98 -> -2.565 | AI98: =AF98*0.4+AF98 -> 2.912 | AJ98: =1-AF98/Z98 -> 0.27017544
B99: simple | C99: 71551 | D99: Dove spray Pear & Aloe 150 ML / 5.07 OZ - 71551 | E99: 1 | F99: 0 | G99: visible | H99: Dove PEAR & ALOE Anti-Perspirant Spray 4oz | I99: Dove invisible dry anti-perspirant gives you serious protection from body odor & sweaty pits, without the deodorant stains. it’s invincible and invisible! provides 48-hour protection. invisibility that holds up - tested on 100 colors with 1/4 moisturizing cream to nourish skin. 0% alcohol, anti-perspirant spray | N99: 1 | O99: 1000 | Z99: 2.85 | AA99: Beauty & Personal Care | AB99: https://fantasydiscountwholesale.com/wp-content/uploads/2023/10/71551.jpeg | AC99: 3-4 | AD99: 6 | AE99: =AD99 -> 6 | AF99: 2.05 | AG99: =AF99*0.39+AF99 -> 2.8495 | AH99: =Z99*0.1-Z99 -> -2.565 | AI99: =AF99*0.4+AF99 -> 2.87 | AJ99: =1-AF99/Z99 -> 0.28070175
B100: simple | C100: 48888 | D100: Axe Black - 48888 | E100: 1 | F100: 0 | G100: visible | H100: Axe Black - 48888 | I100: Axe Black – 48888 features a subtle, refined fragrance with notes of bergamot, rosemary, and cedarwood. Offers long-lasting freshness. Ideal for wholesale to pharmacies, beauty retailers, and men’s grooming sections. | N100: 1 | O100: 1000 | Z100: 2.29 | AA100: Beauty & Personal Care | AB100: https://fantasydiscountwholesale.com/wp-content/uploads/2025/05/48888-1.jpg | AC100: 3-4 | AD100: 12 | AE100: =AD100 -> 12 | AF100: 1.59 | AG100: =AF100*0.4+AF100 -> 2.226 | AH100: =Z100*0.1-Z100 -> -2.061 | AI100: =AF100*0.4+AF100 -> 2.226 | AJ100: =1-AF100/Z100 -> 0.30567686
...

Sheet significado
A1: ID | B1: Type | C1: SKU | D1: Name | E1: Published | F1: Is featured? | G1: Visibility in catalog | H1: Short description | I1: Description | J1: Date sale price starts | K1: Date sale price ends | L1: Tax status | M1: Tax class | N1: In stock? | O1: Stock | P1: Low stock amount | Q1: Backorders allowed? | R1: Sold individually? | S1: Weight (kg) | T1: Length (cm) | U1: Width (cm) | V1: Height (cm) | W1: Allow customer reviews? | X1: Purchase note | Y1: Sale price | Z1: Regular price | AA1: Categories | AB1: Tags | AC1: Shipping class | AD1: Images | AE1: Download limit | AF1: Download expiry days | AG1: Parent | AH1: Grouped products | AI1: Upsells | AJ1: Cross-sells | AK1: External URL | AL1: Button text | AM1: Position | AN1: Product Location | AO1: Items per Products | AP1: Meta: _ic_cogs_cost | AQ1: Valor(es) del atributo 1 | AR1: Atributo visible 1 | AS1: Atributo global 1 | AT1: Nombre de la descarga 1 | AU1: URL de la descarga 1
I13: UPDATE CATALOGO: SHEETS-DOWLOAD\ WEB-PRODUCT-IMPORTS-FILE-EXISTING PRODUST

Sheet Significado-Catalogo
A1: ID | B1: Definición | C1: Tipo | D1: Definición | E1: SKU | F1: Definición | G1: Name | H1: Publicado | I1: Definición | J1: ¿Está destacado? | K1: Definición | L1: Visibilidad en el catálogo | M1: Definición | N1: Short Description | O1: Description | P1: Date sale price starts | Q1: Definición | R1: Date sale price ends | S1: Definición | T1: Tax status | U1: Tax class | V1: Definición | W1: Regular Price | X1: Categories | Y1: Images | Z1: In stock? | AA1: Definición | AB1: Stock | AC1: Items per Products | AD1: Definición | AE1: Meta: _ic_cogs_cost | AF1: Definición
A2: Identificacion del producto | B2: Numero unico e irrepetible de cada producto | C2: external | D2: productos afiliados | E2: stock keeping unit | F2: código de referencia | G2: Nombde del producto | H2: -1 | I2: borrador | J2: 0 | K2: no | L2: hidden | M2: oculto | N2: Descripcion corta del producto | O2: Descripcion completa del producto que se muestra en la pagina del producto | P2: 2021-02-24 | Q2: sin hora | R2: 2021-02-24 | S2: sin hora | T2: Taxable o se deja en blanco sino es taxable | U2: parent | V2: si es producto con variante y es igual que el padre | W2: Precio Regular | X2: Categoria del producto | Y2: Link o URL de la imagen alojada en Wordpress | Z2: 0 | AA2: Agotado | AB2: Cantidad de articulos del mismo producto | AC2: Items por products | AD2: Cantidad mínima a ser vendida por producto | AE2: Cost of Goods | AF2: Costo inicial del producto antes de la venta
C3: simple | D3: sin variantes | H3: 0 | I3: no | J3: 1 | K3: si | L3: visible | M3: visible | P3: 2021-02-24 0:00:00 | Q3: con hora | R3: 2021-02-24 0:00:00 | S3: con hora | U3: Estándar | V3: padre | Z3: 1 | AA3: Hay existencias
C4: simple, downloadable | D4: sin variantes. Los productos descargables dan acceso a un archivo después de la compra | H4: 1 | I4: si | U4: Tasa cero | V4: padre | Z4: backorder | AA4: Se puede reservar
C5: simple, downloadable, virtual | D5: sin variantes. | U5: Tasa reducida | V5: padre
C6: simple, virtual | D6: sin variantes. Los productos virtuales son intangibles y no se envían | L6: si alguien busca numero si aparece
C7: variable | D7: padre
C8: variation | D8: hijos
C9: variation, downloadable | D9: hijos
C10: variation, downloadable, virtual | D10: hijos
C11: variation, virtual | D11: hijos | I11: Processing
I12: Ready to go
I13: Deliverd
A14: Alpha insights | B14: para manage expenses | I14: Pending payment
A15: Alpha insights / p&l | B15: para ver full reports
A16: Para cargar plantilla | B16: Plantilla-file-dowload-csv / produtcs - import - choose file - continue - run importer. | K16: si hay
A17: Para cargar pagina | B17: product- export- chulo- generate / file - import - upload - browse - wc (import data) | K17: no hay
A18: Crear % (regla) de producto | B18: woocomers - pricing and discount (por cliente) \ VC aetting (general discount) | K18: No hay y no se traera
A19: Crear cupones | B19: Marketing - Coupons - add coupons | K19: falta foto
A20: para ver ventas (Analytics)
A21: cargar precio especial | B21: file- dowload-csv / csp- import-file
A23: - SIN STOCK / SALE OUT OF STOCK

Sheet DOLLAR HOUSE
A1: ='CATALOGO PAGINA'!C1 -> SKU | B1: User | C1: Min Qty | D1: Flat | E1: %
A2: ='CATALOGO PAGINA'!C2 -> FD853 | B2: DOLLAR HOUSE | C2: ='CATALOGO PAGINA'!AE2 -> 6 | D2: ='CATALOGO PAGINA'!AF2*0.13+'CATALOGO PAGINA'!AF2 -> 3.8533
A3: ='CATALOGO PAGINA'!C3 -> FD1013S | B3: DOLLAR HOUSE | C3: ='CATALOGO PAGINA'!AE3 -> 12 | D3: ='CATALOGO PAGINA'!AF3*0.13+'CATALOGO PAGINA'!AF3 -> 0.3277
A4: ='CATALOGO PAGINA'!C4 -> FD1013M | B4: DOLLAR HOUSE | C4: ='CATALOGO PAGINA'!AE4 -> 12 | D4: ='CATALOGO PAGINA'!AF4*0.13+'CATALOGO PAGINA'!AF4 -> 0.3277
A5: ='CATALOGO PAGINA'!C5 -> FD1013L | B5: DOLLAR HOUSE | C5: ='CATALOGO PAGINA'!AE5 -> 12 | D5: ='CATALOGO PAGINA'!AF5*0.13+'CATALOGO PAGINA'!AF5 -> 0.3277
A6: ='CATALOGO PAGINA'!C6 -> CN91092-A | B6: DOLLAR HOUSE | C6: ='CATALOGO PAGINA'!AE6 -> 12 | D6: ='CATALOGO PAGINA'!AF6*0.13+'CATALOGO PAGINA'!AF6 -> 1.1187
A7: ='CATALOGO PAGINA'!C7 -> 41661 | B7: DOLLAR HOUSE | C7: ='CATALOGO PAGINA'!AE7 -> 6 | D7: ='CATALOGO PAGINA'!AF7*0.13+'CATALOGO PAGINA'!AF7 -> 2.3165
A8: ='CATALOGO PAGINA'!C8 -> FD1606 | B8: DOLLAR HOUSE | C8: ='CATALOGO PAGINA'!AE8 -> 12 | D8: ='CATALOGO PAGINA'!AF8*0.13+'CATALOGO PAGINA'!AF8 -> 1.582
A9: ='CATALOGO PAGINA'!C9 -> 801440 | B9: DOLLAR HOUSE | C9: ='CATALOGO PAGINA'!AE9 -> 12 | D9: ='CATALOGO PAGINA'!AF9*0.13+'CATALOGO PAGINA'!AF9 -> 1.1074
A10: ='CATALOGO PAGINA'!C10 -> 8888 | B10: DOLLAR HOUSE | C10: ='CATALOGO PAGINA'!AE10 -> 48 | D10: ='CATALOGO PAGINA'!AF10*0.13+'CATALOGO PAGINA'!AF10 -> 0.4068
A11: ='CATALOGO PAGINA'!C11 -> 6134 | B11: DOLLAR HOUSE | C11: ='CATALOGO PAGINA'!AE11 -> 12 | D11: ='CATALOGO PAGINA'!AF11*0.13+'CATALOGO PAGINA'!AF11 -> 1.5142
A12: ='CATALOGO PAGINA'!C12 -> 8594 | B12: DOLLAR HOUSE | C12: ='CATALOGO PAGINA'!AE12 -> 12 | D12: ='CATALOGO PAGINA'!AF12*0.13+'CATALOGO PAGINA'!AF12 -> 2.0227
A13: ='CATALOGO PAGINA'!C13 -> 7532 | B13: DOLLAR HOUSE | C13: ='CATALOGO PAGINA'!AE13 -> 12 | D13: ='CATALOGO PAGINA'!AF13*0.13+'CATALOGO PAGINA'!AF13 -> 1.1752
... A1692: ='CATALOGO PAGINA'!C1692 -> 02447 | B1692: DOLLAR HOUSE | C1692: ='CATALOGO PAGINA'!AE1692 -> 12 | D1692: ='CATALOGO PAGINA'!AF1692*0.13+'CATALOGO PAGINA'!AF1692 -> 1.0848
A1693: ='CATALOGO PAGINA'!C1693
A1694: ='CATALOGO PAGINA'!C1694
A1695: ='CATALOGO PAGINA'!C1695

Sheet FANTASY DISCOUNT
A1: SKU | B1: User | C1: Min Qty | D1: Flat | E1: %
A2: ='CATALOGO PAGINA'!C2 -> FD853 | B2: FANTASY DISCOUNT | C2: ='CATALOGO PAGINA'!AE2 -> 6 | D2: ='CATALOGO PAGINA'!AF2*0.13+'CATALOGO PAGINA'!AF2 -> 3.8533
A3: ='CATALOGO PAGINA'!C3 -> FD1013S | B3: FANTASY DISCOUNT | C3: ='CATALOGO PAGINA'!AE3 -> 12 | D3: ='CATALOGO PAGINA'!AF3*0.13+'CATALOGO PAGINA'!AF3 -> 0.3277
A4: ='CATALOGO PAGINA'!C4 -> FD1013M | B4: FANTASY DISCOUNT | C4: ='CATALOGO PAGINA'!AE4 -> 12 | D4: ='CATALOGO PAGINA'!AF4*0.13+'CATALOGO PAGINA'!AF4 -> 0.3277
A5: ='CATALOGO PAGINA'!C5 -> FD1013L | B5: FANTASY DISCOUNT | C5: ='CATALOGO PAGINA'!AE5 -> 12 | D5: ='CATALOGO PAGINA'!AF5*0.13+'CATALOGO PAGINA'!AF5 -> 0.3277
A6: ='CATALOGO PAGINA'!C6 -> CN91092-A | B6: FANTASY DISCOUNT | C6: ='CATALOGO PAGINA'!AE6 -> 12 | D6: ='CATALOGO PAGINA'!AF6*0.13+'CATALOGO PAGINA'!AF6 -> 1.1187
A7: ='CATALOGO PAGINA'!C7 -> 41661 | B7: FANTASY DISCOUNT | C7: ='CATALOGO PAGINA'!AE7 -> 6 | D7: ='CATALOGO PAGINA'!AF7*0.13+'CATALOGO PAGINA'!AF7 -> 2.3165
A8: ='CATALOGO PAGINA'!C8 -> FD1606 | B8: FANTASY DISCOUNT | C8: ='CATALOGO PAGINA'!AE8 -> 12 | D8: ='CATALOGO PAGINA'!AF8*0.13+'CATALOGO PAGINA'!AF8 -> 1.582
A9: ='CATALOGO PAGINA'!C9 -> 801440 | B9: FANTASY DISCOUNT | C9: ='CATALOGO PAGINA'!AE9 -> 12 | D9: ='CATALOGO PAGINA'!AF9*0.13+'CATALOGO PAGINA'!AF9 -> 1.1074
A10: ='CATALOGO PAGINA'!C10 -> 8888 | B10: FANTASY DISCOUNT | C10: ='CATALOGO PAGINA'!AE10 -> 48 | D10: ='CATALOGO PAGINA'!AF10*0.13+'CATALOGO PAGINA'!AF10 -> 0.4068
A11: ='CATALOGO PAGINA'!C11 -> 6134 | B11: FANTASY DISCOUNT | C11: ='CATALOGO PAGINA'!AE11 -> 12 | D11: ='CATALOGO PAGINA'!AF11*0.13+'CATALOGO PAGINA'!AF11 -> 1.5142
A12: ='CATALOGO PAGINA'!C12 -> 8594 | B12: FANTASY DISCOUNT | C12: ='CATALOGO PAGINA'!AE12 -> 12 | D12: ='CATALOGO PAGINA'!AF12*0.13+'CATALOGO PAGINA'!AF12 -> 2.0227
A13: ='CATALOGO PAGINA'!C13 -> 7532 | B13: FANTASY DISCOUNT | C13: ='CATALOGO PAGINA'!AE13 -> 12 | D13: ='CATALOGO PAGINA'!AF13*0.13+'CATALOGO PAGINA'!AF13 -> 1.1752
... A1692: ='CATALOGO PAGINA'!C1692 -> 02447 | B1692: FANTASY DISCOUNT | C1692: ='CATALOGO PAGINA'!AE1692 -> 12 | D1692: ='CATALOGO PAGINA'!AF1692*0.13+'CATALOGO PAGINA'!AF1692 -> 1.0848
A1693: ='CATALOGO PAGINA'!C1693
A1694: ='CATALOGO PAGINA'!C1694
A1695: ='CATALOGO PAGINA'!C1695

Sheet attack
A1: ='CATALOGO PAGINA'!C1 -> SKU | B1: User | C1: Min Qty | D1: Flat | E1: %
A2: ='CATALOGO PAGINA'!C2 -> FD853 | B2: ATTACK | C2: ='CATALOGO PAGINA'!AE2 -> 6 | D2: ='CATALOGO PAGINA'!AG2 -> 0.99913
A3: ='CATALOGO PAGINA'!C3 -> FD1013S | B3: ATTACK | C3: ='CATALOGO PAGINA'!AE3 -> 12 | D3: ='CATALOGO PAGINA'!AG3 -> 0.754
A4: ='CATALOGO PAGINA'!C4 -> FD1013M | B4: ATTACK | C4: ='CATALOGO PAGINA'!AE4 -> 12 | D4: ='CATALOGO PAGINA'!AG4 -> 1.247
A5: ='CATALOGO PAGINA'!C5 -> FD1013L | B5: ATTACK | C5: ='CATALOGO PAGINA'!AE5 -> 12 | D5: ='CATALOGO PAGINA'!AG5 -> 1.7458
A6: ='CATALOGO PAGINA'!C6 -> CN91092-A | B6: ATTACK | C6: ='CATALOGO PAGINA'!AE6 -> 12 | D6: ='CATALOGO PAGINA'!AG6 -> 1.386
A7: ='CATALOGO PAGINA'!C7 -> 41661 | B7: ATTACK | C7: ='CATALOGO PAGINA'!AE7 -> 6 | D7: ='CATALOGO PAGINA'!AG7 -> 2.87
A8: ='CATALOGO PAGINA'!C8 -> FD1606 | B8: ATTACK | C8: ='CATALOGO PAGINA'!AE8 -> 12 | D8: ='CATALOGO PAGINA'!AG8 -> 2.8
A9: ='CATALOGO PAGINA'!C9 -> 801440 | B9: ATTACK | C9: ='CATALOGO PAGINA'!AE9 -> 12 | D9: ='CATALOGO PAGINA'!AG9 -> 1.372
A10: ='CATALOGO PAGINA'!C10 -> 8888 | B10: ATTACK | C10: ='CATALOGO PAGINA'!AE10 -> 48 | D10: ='CATALOGO PAGINA'!AG10 -> 0.468
A11: ='CATALOGO PAGINA'!C11 -> 6134 | B11: ATTACK | C11: ='CATALOGO PAGINA'!AE11 -> 12 | D11: ='CATALOGO PAGINA'!AG11 -> 1.675
A12: ='CATALOGO PAGINA'!C12 -> 8594 | B12: ATTACK | C12: ='CATALOGO PAGINA'!AE12 -> 12 | D12: ='CATALOGO PAGINA'!AG12 -> 2.2375
A13: ='CATALOGO PAGINA'!C13 -> 7532 | B13: ATTACK | C13: ='CATALOGO PAGINA'!AE13 -> 12 | D13: ='CATALOGO PAGINA'!AG13 -> 1.3
... A1692: ='CATALOGO PAGINA'!C1692 -> 02447 | B1692: ATTACK | C1692: ='CATALOGO PAGINA'!AE1692 -> 12 | D1692: ='CATALOGO PAGINA'!AG1692 -> 1.2864
A1693: ='CATALOGO PAGINA'!C1693
A1694: ='CATALOGO PAGINA'!C1694
A1695: ='CATALOGO PAGINA'!C1695

Sheet next level
A1: SKU | B1: User | C1: Min Qty | D1: Flat | E1: %
A2: ='CATALOGO PAGINA'!C2 -> FD853 | B2: Next level | C2: ='CATALOGO PAGINA'!AE2 -> 6 | D2: ='CATALOGO PAGINA'!AG2 -> 0.99913
A3: ='CATALOGO PAGINA'!C3 -> FD1013S | B3: Next level | C3: ='CATALOGO PAGINA'!AE3 -> 12 | D3: ='CATALOGO PAGINA'!AG3 -> 0.754
A4: ='CATALOGO PAGINA'!C4 -> FD1013M | B4: Next level | C4: ='CATALOGO PAGINA'!AE4 -> 12 | D4: ='CATALOGO PAGINA'!AG4 -> 1.247
A5: ='CATALOGO PAGINA'!C5 -> FD1013L | B5: Next level | C5: ='CATALOGO PAGINA'!AE5 -> 12 | D5: ='CATALOGO PAGINA'!AG5 -> 1.7458
A6: ='CATALOGO PAGINA'!C6 -> CN91092-A | B6: Next level | C6: ='CATALOGO PAGINA'!AE6 -> 12 | D6: ='CATALOGO PAGINA'!AG6 -> 1.386
A7: ='CATALOGO PAGINA'!C7 -> 41661 | B7: Next level | C7: ='CATALOGO PAGINA'!AE7 -> 6 | D7: ='CATALOGO PAGINA'!AG7 -> 2.87
A8: ='CATALOGO PAGINA'!C8 -> FD1606 | B8: Next level | C8: ='CATALOGO PAGINA'!AE8 -> 12 | D8: ='CATALOGO PAGINA'!AG8 -> 2.8
A9: ='CATALOGO PAGINA'!C9 -> 801440 | B9: Next level | C9: ='CATALOGO PAGINA'!AE9 -> 12 | D9: ='CATALOGO PAGINA'!AG9 -> 1.372
A10: ='CATALOGO PAGINA'!C10 -> 8888 | B10: Next level | C10: ='CATALOGO PAGINA'!AE10 -> 48 | D10: ='CATALOGO PAGINA'!AG10 -> 0.468
A11: ='CATALOGO PAGINA'!C11 -> 6134 | B11: Next level | C11: ='CATALOGO PAGINA'!AE11 -> 12 | D11: ='CATALOGO PAGINA'!AG11 -> 1.675
A12: ='CATALOGO PAGINA'!C12 -> 8594 | B12: Next level | C12: ='CATALOGO PAGINA'!AE12 -> 12 | D12: ='CATALOGO PAGINA'!AG12 -> 2.2375
A13: ='CATALOGO PAGINA'!C13 -> 7532 | B13: Next level | C13: ='CATALOGO PAGINA'!AE13 -> 12 | D13: ='CATALOGO PAGINA'!AG13 -> 1.3
... A1634: ='CATALOGO PAGINA'!C1634 -> 1977R | B1634: Next level | C1634: ='CATALOGO PAGINA'!AE1634 -> 12 | D1634: ='CATALOGO PAGINA'!AG1634 -> 0.686
A1635: ='CATALOGO PAGINA'!C1634 -> 1977R | B1635: Next level | C1635: ='CATALOGO PAGINA'!AE1635 -> 12 | D1635: ='CATALOGO PAGINA'!AG1635 -> 0.7473
A1636: ='CATALOGO PAGINA'!C1635 -> 1417R | B1636: Next level | C1636: ='CATALOGO PAGINA'!AE1636 -> 12 | D1636: ='CATALOGO PAGINA'!AG1636 -> 0.7473
A1637: ='CATALOGO PAGINA'!C1636 -> 1418R | B1637: Next level | C1637: ='CATALOGO PAGINA'!AE1637 -> 12 | D1637: ='CATALOGO PAGINA'!AG1637 -> 0.6909
A1638: ='CATALOGO PAGINA'!C1637 -> 0289IV | B1638: Next level | C1638: ='CATALOGO PAGINA'!AE1638 -> 12 | D1638: ='CATALOGO PAGINA'!AG1638 -> 0.6909
A1639: ='CATALOGO PAGINA'!C1638 -> 0002E5 | B1639: Next level | C1639: ='CATALOGO PAGINA'!AE1639 -> 12 | D1639: ='CATALOGO PAGINA'!AG1639 -> 0.6909
A1640: ='CATALOGO PAGINA'!C1639 -> 0537R12 | B1640: Next level | C1640: ='CATALOGO PAGINA'!AE1640 -> 12 | D1640: ='CATALOGO PAGINA'!AG1640 -> 0.6909
A1641: ='CATALOGO PAGINA'!C1640 -> 0290IV | B1641: Next level | C1641: ='CATALOGO PAGINA'!AE1641 -> 12 | D1641: ='CATALOGO PAGINA'!AG1641 -> 0.6909
A1642: ='CATALOGO PAGINA'!C1641 -> 0803R6 | B1642: Next level | C1642: ='CATALOGO PAGINA'!AE1642 -> 12 | D1642: ='CATALOGO PAGINA'!AG1642 -> 0.6909
A1643: ='CATALOGO PAGINA'!C1642 -> 0708R12 | B1643: Next level | C1643: ='CATALOGO PAGINA'!AE1643 -> 6 | D1643: ='CATALOGO PAGINA'!AG1643 -> 0.7473
A1644: ='CATALOGO PAGINA'!C1643 -> HM65082 | B1644: Next level | C1644: ='CATALOGO PAGINA'!AE1644 -> 6 | D1644: ='CATALOGO PAGINA'!AG1644 -> 1.05
A1645: ='CATALOGO PAGINA'!C1644 -> 378537 | B1645: Next level | C1645: ='CATALOGO PAGINA'!AE1645 -> 12 | D1645: ='CATALOGO PAGINA'!AG1645 -> 3.04885
A1646: ='CATALOGO PAGINA'!C1645 -> 6570 | B1646: Next level | C1646: ='CATALOGO PAGINA'!AE1646 -> 12 | D1646: ='CATALOGO PAGINA'!AG1646 -> 3.04885
... A1692: ='CATALOGO PAGINA'!C1691 -> 02445 | B1692: Next level | C1692: ='CATALOGO PAGINA'!AE1692 -> 12 | D1692: ='CATALOGO PAGINA'!AG1692 -> 1.2864
A1693: ='CATALOGO PAGINA'!C1692 -> 02447 | B1693: Next level | C1693: ='CATALOGO PAGINA'!AE1693
A1694: ='CATALOGO PAGINA'!C1693
A1695: ='CATALOGO PAGINA'!C1694

Sheet GOVERNMENT
A1: SKU | B1: User | C1: Min Qty | D1: Flat | E1: %
A2: ='CATALOGO PAGINA'!C2 -> FD853 | B2: GOVERNMENT | C2: ='CATALOGO PAGINA'!AE2 -> 6 | D2: ='CATALOGO PAGINA'!AG2 -> 0.99913
A3: ='CATALOGO PAGINA'!C3 -> FD1013S | B3: GOVERNMENT | C3: ='CATALOGO PAGINA'!AE3 -> 12 | D3: ='CATALOGO PAGINA'!AG3 -> 0.754
A4: ='CATALOGO PAGINA'!C4 -> FD1013M | B4: GOVERNMENT | C4: ='CATALOGO PAGINA'!AE4 -> 12 | D4: ='CATALOGO PAGINA'!AG4 -> 1.247
A5: ='CATALOGO PAGINA'!C5 -> FD1013L | B5: GOVERNMENT | C5: ='CATALOGO PAGINA'!AE5 -> 12 | D5: ='CATALOGO PAGINA'!AG5 -> 1.7458
A6: ='CATALOGO PAGINA'!C6 -> CN91092-A | B6: GOVERNMENT | C6: ='CATALOGO PAGINA'!AE6 -> 12 | D6: ='CATALOGO PAGINA'!AG6 -> 1.386
A7: ='CATALOGO PAGINA'!C7 -> 41661 | B7: GOVERNMENT | C7: ='CATALOGO PAGINA'!AE7 -> 6 | D7: ='CATALOGO PAGINA'!AG7 -> 2.87
A8: ='CATALOGO PAGINA'!C8 -> FD1606 | B8: GOVERNMENT | C8: ='CATALOGO PAGINA'!AE8 -> 12 | D8: ='CATALOGO PAGINA'!AG8 -> 2.8
A9: ='CATALOGO PAGINA'!C9 -> 801440 | B9: GOVERNMENT | C9: ='CATALOGO PAGINA'!AE9 -> 12 | D9: ='CATALOGO PAGINA'!AG9 -> 1.372
A10: ='CATALOGO PAGINA'!C10 -> 8888 | B10: GOVERNMENT | C10: ='CATALOGO PAGINA'!AE10 -> 48 | D10: ='CATALOGO PAGINA'!AG10 -> 0.468
A11: ='CATALOGO PAGINA'!C11 -> 6134 | B11: GOVERNMENT | C11: ='CATALOGO PAGINA'!AE11 -> 12 | D11: ='CATALOGO PAGINA'!AG11 -> 1.675
A12: ='CATALOGO PAGINA'!C12 -> 8594 | B12: GOVERNMENT | C12: ='CATALOGO PAGINA'!AE12 -> 12 | D12: ='CATALOGO PAGINA'!AG12 -> 2.2375
A13: ='CATALOGO PAGINA'!C13 -> 7532 | B13: GOVERNMENT | C13: ='CATALOGO PAGINA'!AE13 -> 12 | D13: ='CATALOGO PAGINA'!AG13 -> 1.3
... A1692: ='CATALOGO PAGINA'!C1692 -> 02447 | B1692: GOVERNMENT | C1692: ='CATALOGO PAGINA'!AE1692 -> 12 | D1692: ='CATALOGO PAGINA'!AG1692 -> 1.2864
A1693: ='CATALOGO PAGINA'!C1693
A1694: ='CATALOGO PAGINA'!C1694
A1695: ='CATALOGO PAGINA'!C1695

Sheet Ramdelsa
A1: SKU | B1: User | C1: Min Qty | D1: Flat | E1: %
A2: ='CATALOGO PAGINA'!C2 -> FD853 | B2: Ramdelsa | C2: ='CATALOGO PAGINA'!AE2 -> 6 | D2: ='CATALOGO PAGINA'!AG2 -> 0.99913
A3: ='CATALOGO PAGINA'!C3 -> FD1013S | B3: Ramdelsa | C3: ='CATALOGO PAGINA'!AE3 -> 12 | D3: ='CATALOGO PAGINA'!AG3 -> 0.754
A4: ='CATALOGO PAGINA'!C4 -> FD1013M | B4: Ramdelsa | C4: ='CATALOGO PAGINA'!AE4 -> 12 | D4: ='CATALOGO PAGINA'!AG4 -> 1.247
A5: ='CATALOGO PAGINA'!C5 -> FD1013L | B5: Ramdelsa | C5: ='CATALOGO PAGINA'!AE5 -> 12 | D5: ='CATALOGO PAGINA'!AG5 -> 1.7458
A6: ='CATALOGO PAGINA'!C6 -> CN91092-A | B6: Ramdelsa | C6: ='CATALOGO PAGINA'!AE6 -> 12 | D6: ='CATALOGO PAGINA'!AG6 -> 1.386
A7: ='CATALOGO PAGINA'!C7 -> 41661 | B7: Ramdelsa | C7: ='CATALOGO PAGINA'!AE7 -> 6 | D7: ='CATALOGO PAGINA'!AG7 -> 2.87
A8: ='CATALOGO PAGINA'!C8 -> FD1606 | B8: Ramdelsa | C8: ='CATALOGO PAGINA'!AE8 -> 12 | D8: ='CATALOGO PAGINA'!AG8 -> 2.8
A9: ='CATALOGO PAGINA'!C9 -> 801440 | B9: Ramdelsa | C9: ='CATALOGO PAGINA'!AE9 -> 12 | D9: ='CATALOGO PAGINA'!AG9 -> 1.372
A10: ='CATALOGO PAGINA'!C10 -> 8888 | B10: Ramdelsa | C10: ='CATALOGO PAGINA'!AE10 -> 48 | D10: ='CATALOGO PAGINA'!AG10 -> 0.468
A11: ='CATALOGO PAGINA'!C11 -> 6134 | B11: Ramdelsa | C11: ='CATALOGO PAGINA'!AE11 -> 12 | D11: ='CATALOGO PAGINA'!AG11 -> 1.675
A12: ='CATALOGO PAGINA'!C12 -> 8594 | B12: Ramdelsa | C12: ='CATALOGO PAGINA'!AE12 -> 12 | D12: ='CATALOGO PAGINA'!AG12 -> 2.2375
A13: ='CATALOGO PAGINA'!C13 -> 7532 | B13: Ramdelsa | C13: ='CATALOGO PAGINA'!AE13 -> 12 | D13: ='CATALOGO PAGINA'!AG13 -> 1.3
... A1692: ='CATALOGO PAGINA'!C1692 -> 02447 | B1692: Ramdelsa | C1692: ='CATALOGO PAGINA'!AE1692 -> 12 | D1692: ='CATALOGO PAGINA'!AG1692 -> 1.2864
A1693: ='CATALOGO PAGINA'!C1693
A1694: ='CATALOGO PAGINA'!C1694
A1695: ='CATALOGO PAGINA'!C1695
A1696: ='CATALOGO PAGINA'!C1696

Sheet Valores
A1: Tipo | B1: Definición | C1: Publicado | D1: Definición | E1: ¿Está destacado? | F1: Definición | G1: Visibilidad en el catálogo | H1: Definición | I1: Fecha de inicio/fin del precio rebajado | J1: Definición | K1: Estado del impuesto | L1: Clase del impuesto | M1: Definición | N1: ¿En inventario? | O1: Definición | P1: ¿Permitir reservar productos agotados? | Q1: ¿Vendido individualmente? | R1: ¿Permitir valoraciones de clientes? | S1: Definición | T1: Atributo visible 1 | U1: Definición | V1: Atributo global 1 | W1: Definición
A2: external | B2: productos afiliados | C2: -1 | D2: borrador | E2: 0 | F2: no | G2: hidden | H2: oculto | I2: 2021-02-24 | J2: sin hora | K2: taxable | L2: parent | M2: si es producto con variante y es igual que el padre | N2: 0 | O2: Agotado | P2: 0 | Q2: 0 | R2: 0 | S2: padre | T2: 0 | U2: No | V2: 0 | W2: No
A3: simple | B3: sin variantes | C3: 0 | D3: no | E3: 1 | F3: si | G3: visible | H3: visible | I3: 2021-02-24 0:00:00 | J3: con hora | L3: Estándar | M3: padre | N3: 1 | O3: Hay existencias | P3: 1 | Q3: 1 | R3: 1 | S3: hijos | T3: 1 | U3: Sí | V3: 1 | W3: Sí
A4: simple, downloadable | B4: sin variantes. Los productos descargables dan acceso a un archivo después de la compra | C4: 1 | D4: si | L4: Tasa cero | M4: padre | N4: backorder | O4: Se puede reservar | Q4: 12
A5: simple, downloadable, virtual | B5: sin variantes. | L5: Tasa reducida | M5: padre
A6: simple, virtual | B6: sin variantes. Los productos virtuales son intangibles y no se envían
A7: variable | B7: padre
A8: variation | B8: hijos
A9: variation, downloadable | B9: hijos
A10: variation, downloadable, virtual | B10: hijos
A11: variation, virtual | B11: hijos
